Workbook

Sheet TABLA RESUMEN
A6: Cuenta de Tipo Dispositivo | B6: Etiquetas de columna
A7: Etiquetas de fila | B7: AIO | C7: DESKTOP | D7: DOCKING | E7: MONITOR | F7: NOTEBOOK | G7: Total general
A8: ANTOFAGASTA | B8: 8 | C8: 16 | D8: 6 | E8: 75 | F8: 41 | G8: 146
A9: ARICA | E9: 2 | G9: 2
A10: CABILDO | C10: 1 | E10: 1 | G10: 2
A11: CALAMA | B11: 3 | C11: 9 | D11: 1 | E11: 10 | F11: 7 | G11: 30 | J11: Q INVENTARIO
A12: CONCEPCIÓN | B12: 8 | C12: 21 | D12: 8 | E12: 81 | F12: 66 | G12: 184
A13: COQUIMBO | B13: 38 | C13: 32 | D13: 22 | E13: 150 | F13: 106 | G13: 348 | J13: =GETPIVOTDATA("Tipo Dispositivo",$A$6) -> 3086
A14: LA LIGUA | B14: 2 | C14: 2 | D14: 3 | E14: 11 | F14: 14 | G14: 32
A15: LAS CABRAS | C15: 1 | E15: 1 | G15: 2
A16: MEJILLONES | C16: 2 | E16: 3 | F16: 1 | G16: 6
A17: OVALLE | B17: 2 | C17: 3 | D17: 2 | E17: 8 | F17: 10 | G17: 25 | J17: OBJETIVO
A18: PICHILEMU | B18: 1 | C18: 1 | E18: 8 | F18: 3 | G18: 13
A19: RANCAGUA | B19: 8 | C19: 28 | D19: 9 | E19: 83 | F19: 52 | G19: 180 | J19: 3500
A20: RENGO | B20: 1 | C20: 3 | E20: 3 | G20: 7
A21: SAN VICENTE DE TAGUA TAGUA | B21: 2 | C21: 1 | E21: 11 | F21: 8 | G21: 22
A22: SANTIAGO | B22: 15 | C22: 42 | D22: 26 | E22: 432 | F22: 446 | G22: 961
A23: TALTAL | C23: 2 | E23: 4 | F23: 2 | G23: 8 | J23: AVANCE
A24: TEMUCO | B24: 13 | C24: 14 | D24: 3 | E24: 55 | F24: 41 | G24: 126
A25: TOCOPILLA | C25: 5 | D25: 1 | E25: 11 | F25: 2 | G25: 19 | J25: =GETPIVOTDATA("Tipo Dispositivo",$A$6)/J19 -> 0.88171429
A26: VICUÑA | B26: 1 | C26: 2 | D26: 3 | E26: 4 | F26: 4 | G26: 14
A27: VIÑA DEL MAR | B27: 2 | C27: 6 | D27: 11 | E27: 23 | F27: 20 | G27: 62
A28: MAULE | E28: 1 | G28: 1
A29: TALCA | B29: 2 | C29: 29 | D29: 17 | E29: 97 | F29: 40 | G29: 185
A30: PUCON | B30: 2 | C30: 1 | E30: 7 | F30: 5 | G30: 15 | J30: Usuarios
A31: CHILLÁN | B31: 1 | C31: 6 | E31: 20 | F31: 14 | G31: 41
A32: LA SERENA | C32: 6 | E32: 5 | G32: 11 | J32: =GETPIVOTDATA("Tipo Dispositivo",$A$6,"Tipo Dispositivo","AIO")+GETPIVOTDATA("Tipo Dispositivo",$A$6,"Tipo Dispositivo","DESKTOP")+GETPIVOTDATA("Tipo Dispositivo",$A$6,"Tipo Dispositivo","NOTEBOOK") -> 1607
A33: TALCAHUANO | B33: 1 | C33: 3 | E33: 3 | G33: 7
A34: SAN FERNANDO | B34: 1 | C34: 4 | E34: 16 | F34: 10 | G34: 31
A35: VILLARRICA | C35: 9 | D35: 2 | E35: 17 | F35: 11 | G35: 39
A36: SAN PEDRO DE LA PAZ | E36: 3 | F36: 6 | G36: 9
A37: LINARES | C37: 5 | D37: 1 | E37: 9 | F37: 10 | G37: 25
A38: COELEMU | C38: 1 | G38: 1
A39: CURACAVI | B39: 3 | E39: 3 | F39: 3 | G39: 9
A40: CORONEL | C40: 3 | E40: 3 | G40: 6
A41: PUENTE ALTO | C41: 8 | F41: 3 | G41: 11
A42: QUIRIHUE | C42: 2 | E42: 9 | F42: 7 | G42: 18
A43: LOS ÁNGELES | C43: 6 | E43: 12 | F43: 6 | G43: 24
A44: COPIAPO | B44: 5 | E44: 6 | F44: 5 | G44: 16
A45: IQUIQUE | B45: 6 | C45: 10 | E45: 38 | F45: 38 | G45: 92
A46: SAN CARLOS | B46: 1 | C46: 1 | G46: 2
A47: SAN JAVIER | B47: 1 | C47: 2 | E47: 1 | G47: 4
A48: SAN CLEMENTE | C48: 2 | E48: 2 | F48: 1 | G48: 5
A49: TALAGANTE | C49: 5 | E49: 3 | F49: 3 | G49: 11
A50: ALTO HOSPICIO | F50: 1 | G50: 1
A51: HUALAÑE | C51: 2 | D51: 2 | E51: 6 | F51: 4 | G51: 14
A52: ALTO HOSPICIO | E52: 1 | G52: 1
A53: PARRAL | C53: 9 | E53: 14 | F53: 8 | G53: 31
A54: CONSTITUCIÓN | C54: 1 | D54: 2 | E54: 1 | F54: 1 | G54: 5
A55: VALLENAR | C55: 2 | E55: 2 | F55: 2 | G55: 6
A56: BUIN | C56: 7 | E56: 14 | F56: 8 | G56: 29
A57: ILLAPEL | C57: 2 | E57: 10 | F57: 8 | G57: 20
A58: LOS VILOS | C58: 2 | E58: 2 | G58: 4
A59: CONSTITUCIÓN | C59: 4 | D59: 1 | E59: 6 | F59: 6 | G59: 17
A60: CURICÓ | C60: 13 | D60: 3 | E60: 20 | F60: 11 | G60: 47
A61: CAUQUENES | C61: 4 | E61: 8 | F61: 6 | G61: 18
A62: CHAÑARAL | E62: 1 | F62: 2 | G62: 3
A63: CALDERA | C63: 1 | E63: 1 | F63: 1 | G63: 3
A64: HUASCO | F64: 1 | G64: 1
A65: TOME | C65: 3 | E65: 4 | F65: 4 | G65: 11
A66: CHAÑARAL | F66: 1 | G66: 1
A67: MOLINA | C67: 2 | E67: 1 | G67: 3
A68: VALLENAR | E68: 1 | G68: 1
A69: PELLEHUE | C69: 1 | D69: 1 | E69: 3 | F69: 5 | G69: 10
A70: SANTA CRUZ | C70: 2 | E70: 4 | F70: 4 | G70: 10
A71: COBQUECURA | C71: 1 | E71: 1 | G71: 2
A72: PUNTA ARENAS | C72: 7 | E72: 22 | F72: 57 | G72: 86
A73: PUERTO NATALES | C73: 6 | E73: 2 | F73: 2 | G73: 10
A74: Total general | B74: 127 | C74: 363 | D74: 124 | E74: 1355 | F74: 1117 | G74: 3086

Sheet Hoja1
A1: Dirección | B1: AVENIDA PRESIDENTE RIESCO N° 5561
A3: Etiquetas de fila | B3: qqq
A4: LUIS SEBASTIAN | B4: =VLOOKUP(A4,[1]Hoja8!$A$1:$F$465,2,FALSE) -> CGE S.A
A5: ADAM PATRICIO CASTILLO SALAS | B5: =VLOOKUP(A5,[1]Hoja8!$A$1:$F$465,2,FALSE) -> CGE Servicios S.A.
A6: ADELIS VIRGINIA MENDEZ VARGAS | B6: =VLOOKUP(A6,[1]Hoja8!$A$1:$F$465,2,FALSE) -> CGE Servicios S.A.
A7: ADOLFO ENRIQUE ALVARADO JELDRES | B7: =VLOOKUP(A7,[1]Hoja8!$A$1:$F$465,2,FALSE) -> CGE Servicios S.A.
A8: ALEJANDRA ANDREA SOLA STEVENSON | B8: =VLOOKUP(A8,[1]Hoja8!$A$1:$F$465,2,FALSE) -> CGE Servicios S.A.
A9: ALEJANDRA ROSARIO APARICIO SEPULVEDA | B9: =VLOOKUP(A9,[1]Hoja8!$A$1:$F$465,2,FALSE) -> CGE Servicios S.A.
A10: ALVARO MALDONADO | B10: =VLOOKUP(A10,[1]Hoja8!$A$1:$F$465,2,FALSE) -> #N/A
A11: ANA CECILIA PACHECO GARRIDO | B11: =VLOOKUP(A11,[1]Hoja8!$A$1:$F$465,2,FALSE) -> CGE Servicios S.A.
A12: ANA MARIA ARIAS ATHANACIU | B12: =VLOOKUP(A12,[1]Hoja8!$A$1:$F$465,2,FALSE) -> CGE Servicios S.A.
A13: ANA MARIA RODRIGUEZ ORELLANA | B13: =VLOOKUP(A13,[1]Hoja8!$A$1:$F$465,2,FALSE) -> CGE Servicios S.A.
A14: ANDREA MARISOL BELTRAN FUENTES | B14: =VLOOKUP(A14,[1]Hoja8!$A$1:$F$465,2,FALSE) -> CGE Servicios S.A.
A15: ANDREA PAZ VIACAVA NAZAR | B15: =VLOOKUP(A15,[1]Hoja8!$A$1:$F$465,2,FALSE) -> CGE Servicios S.A.
... A475: Total general | B475: =VLOOKUP(A475,[1]Hoja8!$A$1:$F$465,2,FALSE) -> #N/A
B476: =VLOOKUP(A476,[1]Hoja8!$A$1:$F$465,2,FALSE) -> #N/A
B477: =VLOOKUP(A477,[1]Hoja8!$A$1:$F$465,2,FALSE) -> #N/A
B478: =VLOOKUP(A478,[1]Hoja8!$A$1:$F$465,2,FALSE) -> #N/A
B479: =VLOOKUP(A479,[1]Hoja8!$A$1:$F$465,2,FALSE) -> #N/A
B480: =VLOOKUP(A480,[1]Hoja8!$A$1:$F$465,2,FALSE) -> #N/A
B481: =VLOOKUP(A481,[1]Hoja8!$A$1:$F$465,2,FALSE) -> #N/A
B482: =VLOOKUP(A482,[1]Hoja8!$A$1:$F$465,2,FALSE) -> #N/A

Sheet CONSOLIDADO
A1: Activo Fijo | B1: Rotulo Entel | C1: Tipo Dispositivo | D1: Unidades | E1: Teléfono | F1: Nombre de Usuario | G1: Usuario de RED | H1: Número de Serie | I1: Hostname | J1: Marca | K1: Modelo | L1: Dirección | M1: Piso | N1: Comuna | O1: Región | P1: Ciudad | Q1: Area | R1: Necesita Alzador | S1: Nombre de usuario Responsable | T1: Tipo Usuario | U1: Observaciones | V1: Observaciones 2 | W1: D | X1: FOTOS
A2: No visible | B2: CGE005656 | C2: NOTEBOOK | D2: 1 | E2: NO | F2: ALEX MAURICIO CEBALLOS DURAN | G2: AMCEBALLOSD | H2: HLZB9W3 | I2: HLZB9W3 | J2: DELL | K2: DELL LATITUDE 7440 | L2: 2 NORTE 798 | M2: 2 | N2: TALCA | O2: MAULE | P2: TALCA | Q2: ATENCIÓN COMERCIAL | R2: NO | S2: Funciona correctamente | T2: INTERNO | X2: https://drive.google.com/open?id=1UYjhZ49z3HhuQyQqfJCrImSWTRT9fn6t
A3: 210000063856-0000 | B3: CGE005487 | C3: MONITOR | D3: 1 | E3: SI | F3: ALEX MAURICIO CEBALLOS DURAN | G3: AMCEBALLOSD | H3: CN 0101CF | I3: NO APLICA | J3: DELL | K3: NO VISIBLE | L3: 2 NORTE 798 | M3: 2 | N3: TALCA | O3: MAULE | P3: TALCA | Q3: ATENCIÓN COMERCIAL | R3: N/A | S3: Funciona correctamente | T3: INTERNO | X3: https://drive.google.com/open?id=1ksr3n7NG98C1Ah1n21iDFfRPlIclUPhl
A4: 210000028136-0000 | B4: CGE007351 | C4: DESKTOP | D4: 1 | E4: NO | F4: CAROL SANDOVAL | G4: CSANDOVAL | H4: MXL1240NZ4 | I4: DTMXL1240NZ4 | J4: HP | K4: 8200 | L4: 2 NORTE 798 | M4: 1 | N4: TALCA | O4: MAULE | P4: TALCA | Q4: ATENCIÓN COMERCIAL | R4: NO | S4: Funciona correctamente | T4: INTERNO | W4: https://drive.google.com/open?id=1Eve0NnLSgy9mqSRjGNcuRfdhoIWIKbg5
A5: 210000022369-0000 | B5: CGE007441 | C5: MONITOR | D5: 1 | E5: SI | F5: CATHERINE ALIAGA | G5: NO APLICA | H5: CN ON445N 74261 09R 2KGS | I5: NO APLICA | J5: DELL | K5: E170SC | L5: 2 NORTE 798 | M5: 2 | N5: TALCA | O5: MAULE | P5: TALCA | Q5: ATENCIÓN COMERCIAL | R5: N/A | S5: Funciona correctamente | T5: INTERNO | W5: https://drive.google.com/open?id=1XfxRjNea402XQg9I41DeRy_PM2GozToe
A6: 210000064187-0000 | B6: CGE006673 | C6: MONITOR | D6: 1 | E6: SI | F6: CESAR PEREZ | G6: NO APLICA | H6: VN 0MDK14 WS700 418 A3BU A02 | I6: NO APLICA | J6: DELL | K6: P2722HE | L6: 2 NORTE 798 | M6: 2 | N6: TALCA | O6: MAULE | P6: TALCA | Q6: ATENCIÓN COMERCIAL | R6: N/A | S6: Funciona correctamente | T6: INTERNO | W6: https://drive.google.com/open?id=16Fff9yD8Zi6ABRYWY3ghIIvFaYfEOqlL
A7: 210000061160-0000 | B7: CGE001478 | C7: NOTEBOOK | D7: 1 | E7: NO | F7: CHRISTIAN VALENZUELA | G7: CVALENZUELAM | H7: 5CD207HCW1 | I7: NB5CD207HCW1 | J7: HP | K7: HP PROBOOK 440 G8 | L7: 2 NORTE 798 | M7: 2 | N7: TALCA | O7: MAULE | P7: TALCA | Q7: ATENCIÓN COMERCIAL | R7: NO | S7: Funciona correctamente | T7: INTERNO | W7: https://drive.google.com/open?id=1Ci_vMFBzTmpHRth_VYaolzm3mA-ACqHf
A8: No visible | B8: NO VISIBLE | C8: MONITOR | D8: 1 | E8: SI | F8: CHRISTIAN VALENZUELA | G8: NO APLICA | H8: CNN7322821 | I8: NO APLICA | J8: HP | K8: NO VISIBLE | L8: 2 NORTE 798 | M8: 2 | N8: TALCA | O8: MAULE | P8: TALCA | Q8: ATENCIÓN COMERCIAL | R8: N/A | S8: Funciona correctamente | T8: INTERNO
A9: 210000028014-0000 | B9: NO POSEE | C9: DESKTOP | D9: 1 | E9: NO | F9: DANIEL BECERRA | G9: EJECUTIVODEDM | H9: MXL1341PFN | I9: DTMXL1341PFN | J9: HP | K9: 8200 | L9: 2 NORTE 798 | M9: 1 | N9: TALCA | O9: MAULE | P9: TALCA | Q9: ATENCIÓN COMERCIAL | R9: NO | S9: Funciona correctamente | T9: INTERNO | W9: https://drive.google.com/open?id=18KT5RhA1EtSc1jadWFCXf3yy_iMA4MQN
A10: 210000064143-0000 | B10: CGE006019 | C10: NOTEBOOK | D10: 1 | E10: NO | F10: DANIELA MUÑOZ | G10: DGMUNOZG | H10: 7ZQRK24 | I10: NB7ZQRK24 | J10: DELL | K10: LATITUDE 5440 | L10: 2 NORTE 798 | M10: 2 | N10: TALCA | O10: MAULE | P10: TALCA | Q10: ATENCIÓN COMERCIAL | R10: NO | S10: Funciona correctamente, sin daños | T10: INTERNO | W10: https://drive.google.com/open?id=1azvWQEUyAAdyBM7rNfcxqo6vgShvnEBY
A11: 210000060388-0000 | B11: NO PRESENTA | C11: MONITOR | D11: 1 | E11: SI | F11: DANIELA MUÑOZ | G11: NO APLICA | H11: 1CR1202Z0 | I11: NO APLICA | J11: HP | K11: P24V G4 FHD | L11: 2 NORTE 798 | M11: 2 | N11: TALCA | O11: MAULE | P11: TALCA | Q11: ATENCIÓN COMERCIAL | S11: Funciona correctamente, sin daños | T11: INTERNO | W11: https://drive.google.com/open?id=1Mfo5XnJauk3fszNzpXXIeAV2R0X-g_9p
A12: 210000066404-0000 | B12: CGE010618 | C12: DESKTOP | D12: 1 | E12: NO | F12: DENISSE ANDREA CANCINO VASQUEZ | G12: DACANCINOV | H12: NO VISIBLE | I12: USUARIO NO SE ENCUENTRA EN LA SUCURSAL | J12: LENOVO | K12: THINKCENTRE | L12: 2 NORTE 798 | M12: 1 | N12: TALCA | O12: MAULE | P12: TALCA | Q12: ATENCIÓN COMERCIAL | R12: NO | T12: INTERNO | W12: https://drive.google.com/open?id=1BUzVzPq2soWMZiz0RahELD6IpBmdsbGo
A13: 210000061076-0000 | B13: CGE001486 | C13: NOTEBOOK | D13: 1 | E13: NO | F13: FABIAN RODRIGUEZ | G13: FRODRIGUEZ | H13: 5CD207HCG5 | I13: NB5CD207HCG5 | J13: HP | K13: HP PROBOOK 440 G8 | L13: 2 NORTE 798 | M13: 2 | N13: TALCA | O13: MAULE | P13: TALCA | Q13: ATENCIÓN COMERCIAL | R13: NO | S13: Funciona correctamente | T13: INTERNO | W13: https://drive.google.com/open?id=1gkznBaGTF2dLimo0rW8cp9lRSavggHGo
A14: 210000027309-0000 | B14: CGE003118 | C14: MONITOR | D14: 1 | E14: SI | F14: FABIAN RODRIGUEZ | G14: NO APLICA | H14: CNC117PWXH | I14: NO APLICA | J14: HP | K14: COMPAC LE1711 | L14: 2 NORTE 798 | M14: 2 | N14: TALCA | O14: MAULE | P14: TALCA | Q14: ATENCIÓN COMERCIAL | R14: N/A | S14: Funciona correctamente | T14: INTERNO | W14: https://drive.google.com/open?id=1K-92ZoXyhiEL8cJS9ImOcOGstQXMdc19
A15: 210000063805-0000 | B15: CGE005481 | C15: MONITOR | D15: 1 | E15: SI | F15: FRANCISCA CASANOVA | G15: FCASANOVA | H15: CN-0101CF | I15: NO APLICA | J15: DELL | K15: DELL 24 | L15: 2 NORTE 798 | M15: 2 | N15: TALCA | O15: MAULE | P15: TALCA | R15: N/A | S15: Funciona correctamente | T15: INTERNO | X15: https://drive.google.com/open?id=1OWLjQIc9hFuJw34P1F0AeeZZLsyDPjBW
A16: 210000049155-0000 | B16: NO PRESENTA | C16: NOTEBOOK | D16: 1 | E16: NO | F16: FRANCISCA CASANOVA | G16: FCASANOVA | H16: NB-5CG7411CGS | I16: NB-5CG7411CGS | J16: HP | K16: HO ELITEBOOK | L16: 2 NORTE 798 | M16: 2 | N16: TALCA | O16: MAULE | P16: TALCA | Q16: ATENCIÓN COMERCIAL | R16: NO | S16: Funciona correctamente, sin daños | T16: INTERNO | W16: https://drive.google.com/open?id=13MrZyLTtBgOQOSfaP22MTOMjCpHu57iM
A17: 210000042619-0000 | B17: NO VISIBLE | C17: DOCKING | D17: 1 | E17: NO | F17: FRANCISCA CASANOVA | G17: NO APLICA | H17: 5CG532W7M2 | I17: NO APLICA | J17: HP | K17: 2013 ULTRASLIM DOCKINGSTATION | L17: 2 NORTE 798 | M17: 2 | N17: TALCA | O17: MAULE | P17: TALCA | Q17: ATENCIÓN COMERCIAL | R17: N/A | S17: Funciona correctamente | T17: INTERNO | W17: https://drive.google.com/open?id=1KgdVXe50NPjhenUAwPZB2l8MQhpt3zJ3
A18: 210000021877-0000 | B18: CGE007341 | C18: DESKTOP | D18: 1 | E18: NO | F18: ISABEL ALEJANDRA GARAUD CARRASCO | G18: IAGARAUDC | H18: MXL1341PF0 | I18: DTMXL1341PF0 | J18: HP | K18: HPCOMPAQ 8200 ELITE SMALLFORM FACTOR | L18: 2 NORTE 798 | M18: 1 | N18: TALCA | O18: MAULE | P18: TALCA | Q18: ATENCIÓN COMERCIAL | R18: N/A | S18: Funciona correctamente | T18: INTERNO | W18: https://drive.google.com/open?id=1wDdVFioG9-W2i72U5fOTxSYcqZRhfMaA
A19: 210000026553-0000 | B19: CGE007338 | C19: MONITOR | D19: 1 | E19: SI | F19: ISABEL ALEJANDRA GARAUD CARRASCO | G19: N/A | H19: CNC115PRSF | I19: N/A | J19: HP | K19: COMPAQ LE1711 | L19: 2 NORTE 798 | M19: 1 | N19: TALCA | O19: MAULE | P19: TALCA | Q19: ATENCIÓN COMERCIAL | R19: N/A | T19: INTERNO | W19: https://drive.google.com/open?id=1UFsSYBUkc3ROuJjqM3lcpY27xcH5ICCS
A20: 210000027733-0000 | B20: CGE007348 | C20: DESKTOP | D20: 1 | E20: NO | F20: LAURA ANDREA HERRERA ESPINOZA | G20: LAHERRERAE | H20: MXL13611JH | I20: DTMXL13611JH | J20: HP | K20: NO VISIBLE | L20: 2 NORTE 798 | M20: 1 | N20: TALCA | O20: MAULE | P20: TALCA | Q20: ATENCIÓN COMERCIAL | R20: NO | S20: Funciona correctamente | T20: INTERNO | W20: https://drive.google.com/open?id=1aRrj-kv46hiwfTzHuok2Wl0QmrhOiTBc
A21: 210000027224-0000 | B21: CGE007347 | C21: MONITOR | D21: 1 | E21: SI | F21: LAURA ANDREA HERRERA ESPINOZA | G21: N/A | H21: CNC118QSK6 | I21: N/A | J21: HP | K21: COMPAQ LE1711 | L21: 2 NORTE 798 | M21: 1 | N21: TALCA | O21: MAULE | P21: TALCA | Q21: ATENCIÓN COMERCIAL | R21: N/A | T21: INTERNO | W21: https://drive.google.com/open?id=1XRPnJhBah4l1YyNhYj2TUR7HTS8QmV5u
A22: 210000002744-0000 | B22: CGE007353 | C22: MONITOR | D22: 1 | E22: SI | F22: LAURA ANDREA HERRERA ESPINOZA | G22: N/A | H22: CNC118QRQ8 | I22: N/A | J22: HP | K22: COMPAQ LE1711 | L22: 2 NORTE 798 | M22: 1 | N22: TALCA | O22: MAULE | P22: TALCA | Q22: ATENCIÓN COMERCIAL | R22: N/A | T22: INTERNO | W22: https://drive.google.com/open?id=1TPfG2U-1zrIaIqDrGFAwYMyH-jZsJD_4
A23: 210000066506-0000 | B23: CGE010550 | C23: DESKTOP | D23: 1 | E23: NO | F23: LUISA GALVEZ | G23: LIGALVEZT | H23: NO VISIBLE | I23: PERSONA DEL EQUIPO AUSENTE | K23: TINKCENTRE | L23: 2 NORTE 798 | M23: 1 | N23: TALCA | O23: MAULE | P23: TALCA | Q23: ATENCIÓN COMERCIAL | R23: N/A | S23: Funciona correctamente | T23: INTERNO | W23: https://drive.google.com/open?id=1Yi2VoyEI3azCrG33o4KMfwbwmcOewNlN
A24: 210000062155-0000 | B24: CGE000091 | C24: DESKTOP | D24: 1 | E24: NO | F24: LUISA GALVEZ | G24: LIGALVEZT | H24: 4CE238B2BB | I24: DT4CE238B2BB | J24: HP | K24: HP PRO SFF 400 G9 | L24: 2 NORTE 798 | M24: 1 | N24: TALCA | O24: MAULE | P24: TALCA | Q24: ATENCIÓN COMERCIAL | R24: N/A | S24: Funciona correctamente | T24: INTERNO | W24: https://drive.google.com/open?id=1E0ir60yQrPmPz--4lwOGXA-GYlyDtBCa
A25: 210000013561-0000 | B25: CGE001393 | C25: MONITOR | D25: 1 | E25: SI | F25: LUISA IVONNE GALVEZ TAPIA | G25: N/A | H25: CN-0U072N-64180-99S-120S | I25: N/A | J25: DELL | K25: E170SC | L25: 2 NORTE 798 | M25: 1 | N25: TALCA | O25: MAULE | P25: TALCA | Q25: ATENCIÓN COMERCIAL | R25: N/A | T25: INTERNO | W25: https://drive.google.com/open?id=1Oi0SIcB8GzymuRh2pP7_D9TINNwu5saH
A26: 510000006872-0000 | B26: NO TIENE | C26: TELEFONO IP | D26: 1 | E26: NO | F26: LUISA IVONNE GALVEZ TAPIA | G26: N/A | H26: FCH12479FTL | I26: N/A | J26: CISCO | K26: CP 7911G | L26: 2 NORTE 798 | M26: 1 | N26: TALCA | O26: MAULE | P26: TALCA | Q26: ATENCIÓN COMERCIAL | R26: N/A | T26: INTERNO | W26: https://drive.google.com/open?id=1-sXUB6CVZL8-eEs2uGPXD4WWytPMUgG1
A27: 510000006867-0000 | B27: NO TIENE | C27: TELEFONO IP | D27: 1 | E27: NO | F27: LUISA IVONNE GALVEZ TAPIA | G27: N/A | H27: FCH12479H8Z | I27: N/A | J27: CISCO | K27: CP7911G | L27: 2 NORTE 798 | M27: 1 | N27: TALCA | O27: MAULE | P27: TALCA | Q27: ATENCIÓN COMERCIAL | R27: N/A | T27: INTERNO | W27: https://drive.google.com/open?id=1ONJmC46SgBN3Jtxkjy6Xpm_wmeIki6V5
A28: 210000045769-0000 | B28: CGE002684 | C28: NOTEBOOK | D28: 1 | E28: NO | F28: LUSGARDA VERGARA | G28: LVERGARA | H28: 5CG8402GOQ | I28: NB5CG8402GOQ | J28: HP | K28: ELITEBOOK 840 | L28: 2 NORTE 798 | M28: 2 | N28: TALCA | O28: MAULE | P28: TALCA | Q28: ATENCIÓN COMERCIAL | R28: SI | S28: Funciona correctamente | T28: INTERNO | W28: https://drive.google.com/open?id=1cwbcfjBnayskgSQb2laNOkFOTsOtOHFN
A29: 210000060423-0000 | B29: NO PRESENTA | C29: MONITOR | D29: 1 | E29: SI | F29: LUSGARDA VERGARA | G29: LVERGARA | H29: 1CR12102ZT | I29: NO APLICA | J29: HP | K29: P24V G4 FHD | L29: 2 NORTE 798 | M29: 2 | N29: TALCA | O29: MAULE | P29: TALCA | Q29: ATENCIÓN COMERCIAL | S29: Funciona correctamente | T29: INTERNO | W29: https://drive.google.com/open?id=1sMoJe4mq_b6D9ymj6ucrktXXqUqP6cvE
A30: NO TIENE | B30: NO TIENE | C30: NOTEBOOK | D30: 1 | E30: NO | F30: MARCIA VARAS VENEGAS | G30: N/A | H30: 5CD4484GRS | I30: N/A | J30: HP | K30: PROBOOK450 G10 | L30: 2 NORTE 798 | M30: 1 | N30: TALCA | O30: MAULE | P30: TALCA | Q30: ATENCIÓN COMERCIAL | R30: NO | S30: equipo de apoyo terreno | T30: INTERNO
A31: NO TIENE | B31: NO TIENE | C31: NOTEBOOK | D31: 1 | E31: NO | F31: MARCIA VARAS VENEGAS | G31: NO APLICA | H31: 5CD5033GL2 | I31: NO APLICA | J31: HP | K31: HP PROBOOK 450 G10 | L31: 2 NORTE 798 | M31: 1 | N31: TALCA | O31: MAULE | P31: TALCA | Q31: ATENCIÓN COMERCIAL | R31: NO | S31: Equipo apoyo terreno | T31: INTERNO | W31: https://drive.google.com/open?id=1M-np0U-PI9K62-EAzkMoO7U2WRiz1qjx
A32: 210000066519-0000 | B32: CGE010549 | C32: DESKTOP | D32: 1 | E32: NO | F32: MARCIA VARAS VENEGAS | G32: EJECUTIVOMVV | H32: AIOMP2GDJ1J | I32: AIOMP2GDJ1J | J32: LENOVO | K32: LENOVO TINKCENTRE | L32: 2 NORTE 798 | M32: 1 | N32: TALCA | O32: MAULE | P32: TALCA | Q32: ATENCIÓN COMERCIAL | R32: N/A | S32: Funciona correctamente, sin daños | T32: INTERNO | W32: https://drive.google.com/open?id=1rDTeUZUgveNzyfig47HU4451lsRYF36L
A33: 510000005808-0000 | B33: NO TIENE | C33: TELEFONO IP | D33: 1 | E33: NO | F33: MARCIA VARAS VENEGAS | G33: N/A | H33: FCH1249938T | I33: N/A | J33: CISCO | K33: IP PHONE CP 7911G | L33: 2 NORTE 798 | M33: 1 | N33: TALCA | O33: MAULE | P33: TALCA | Q33: ATENCIÓN COMERCIAL | R33: N/A | T33: INTERNO | W33: https://drive.google.com/open?id=1uMlpIIaH7OIbYbHYdK82SkkT08eCwrwt
A34: 510000006758-0000 | B34: NO TIENE | C34: TELEFONO IP | D34: 1 | E34: SI | F34: MARCIA VARAS VENEGAS | G34: N/A | H34: FCH1246842E | I34: N/A | J34: CISCO | K34: IP PHONE 7941 | L34: 2 NORTE 798 | M34: 1 | N34: TALCA | O34: MAULE | P34: TALCA | Q34: ATENCIÓN COMERCIAL | R34: N/A | T34: INTERNO | W34: https://drive.google.com/open?id=1VZHGaPgWsu8PbFZOSz8GrBjxxMZ5SU8V
A35: 510000005999-0000 | B35: NO TIENE | C35: MONITOR | D35: 1 | E35: SI | F35: MARÍA FUENTES | G35: N/A | H35: FCH1246909N | I35: N/A | J35: CISCO | K35: IP PHONE 7900 | L35: 2 NORTE 798 | M35: 1 | N35: TALCA | O35: MAULE | P35: TALCA | Q35: ATENCIÓN COMERCIAL | R35: N/A | T35: INTERNO | W35: https://drive.google.com/open?id=1tGcpQEyScIxa65oeqIwmQi4G66BQgUiP
A36: 210000036481-0000 | B36: CGE007344 | C36: MONITOR | D36: 1 | E36: SI | F36: MARIA VERONICA | G36: N/A | H36: CNC145P306 | I36: N/A | J36: HP | K36: COMPAQ LE1711 | L36: 2 NORTE 798 | M36: 1 | N36: TALCA | O36: MAULE | P36: TALCA | Q36: ATENCIÓN COMERCIAL | R36: N/A | T36: INTERNO | W36: https://drive.google.com/open?id=1wvtijdNUgdhLfRqA2-HBIH_bfOIrZ-en
A37: 510000005803-0000 | B37: NO TIENE | C37: TELEFONO IP | D37: 1 | E37: NO | F37: MARIA VERONICA | G37: N/A | H37: FCH12479KZH | I37: N/A | J37: CISCO | K37: IP PHONE 7911 | L37: 2 NORTE 798 | M37: 1 | N37: TALCA | O37: MAULE | P37: TALCA | Q37: ATENCIÓN COMERCIAL | R37: N/A | T37: INTERNO | W37: https://drive.google.com/open?id=1BHhq-6BU7lHrRTpvTm9-beVx5_-JLtlC
A38: 210000027319-0000 | B38: NO POSEE | C38: MONITOR | D38: 1 | E38: SI | F38: PABLO FUENZALIDA | G38: PAFUENZALIDAP | H38: CNC115T2F7 | I38: NO APLICA | J38: HP | K38: LE1711 | L38: 2 NORTE 798 | M38: 2 | N38: TALCA | O38: MAULE | P38: TALCA | Q38: ATENCIÓN COMERCIAL | R38: N/A | S38: Funciona correctamente, sin daños | T38: INTERNO | W38: https://drive.google.com/open?id=1_j_Rf1BdRQfftgnNTf04vBZ9cZjDBbZf
A39: 210000027462-0000 | B39: CGE073343 | C39: MONITOR | D39: 1 | E39: SI | F39: PAULA VERENNA VALDIVIA MUÑOZ | G39: N/A | H39: CNC118QSHZ | I39: N/A | J39: HP | K39: COMPAQ LE1711 | L39: 2 NORTE 798 | M39: 1 | N39: TALCA | O39: MAULE | P39: TALCA | Q39: ATENCIÓN COMERCIAL | R39: N/A | T39: INTERNO | W39: https://drive.google.com/open?id=1Rs3Xj9MXMLTdcsZt4OmqBz6uGaLG1Dgk
A40: 210000024836-0000 | B40: CGE002651 | C40: MONITOR | D40: 1 | E40: SI | F40: RODRIGO ANDRES ASTUDILLO GONZALEZ | G40: RAASTUDILLOG | H40: CNC114QD9P | I40: NO APLICA | J40: HP | K40: LE1711 | L40: 2 NORTE 798 | M40: 2 | N40: TALCA | O40: MAULE | P40: TALCA | Q40: ATENCIÓN COMERCIAL | R40: N/A | S40: Funciona correctamente, sin daños | T40: INTERNO | W40: https://drive.google.com/open?id=1YvVWMHGi0F2TRAQ-Uq4BT09-wYNBZ76_
A41: No visible | B41: CGE002649 | C41: NOTEBOOK | D41: 1 | E41: NO | F41: RODRIGO ANDRES ASTUDILLO GONZALEZ | G41: RAASTUDILLOG | H41: 5CD207HF5Q | I41: NB5CD207HF5Q | J41: HP | K41: HP PROBOOK 440 G8 | L41: 2 NORTE 798 | M41: 2 | N41: TALCA | O41: MAULE | P41: TALCA | Q41: ATENCIÓN COMERCIAL | R41: SI | S41: Funciona correctamente, daños estético | T41: INTERNO | W41: https://drive.google.com/open?id=15mVPtgtXti4NAjoiYpYK7XDLMqx3ILPw
A42: 510000003867-0000 | B42: CGE000903 | C42: TELEFONO IP | D42: 1 | E42: SI | F42: RODRIGO ANDRES ASTUDILLO GONZALEZ | G42: RAASTUDILLOG | H42: FCH12468XUK | I42: NO APLICA | J42: CISCO | K42: CISCO IP PHONE 7941 | L42: 2 NORTE 798 | M42: 2 | N42: TALCA | O42: MAULE | P42: TALCA | Q42: ATENCIÓN COMERCIAL | R42: N/A | S42: Funciona correctamente | T42: INTERNO | W42: https://drive.google.com/open?id=1JCDi7q2jj71Bjnz3pplzWRgEkrSWTTMa
A43: 510000007080-0000 | B43: NO PRESENTA | C43: TELEFONO IP | D43: 1 | E43: SI | F43: SIN USUARIO FIJO | G43: SIN USUARIO FIJO | H43: FCH124B3KL | I43: NO APLICA | J43: CISCO | K43: CISCO IP PHONE 7961 | L43: 2 NORTE 798 | M43: 2 | N43: TALCA | O43: MAULE | P43: TALCA | Q43: ATENCIÓN COMERCIAL | R43: N/A | S43: Funciona correctamente, sin daños | T43: INTERNO | W43: https://drive.google.com/open?id=16RfimhoMUCiT2L3NX5jra0gtAUyqVsVR
A44: 210000052353-0000 | B44: NO VISIBLE | C44: DESKTOP | D44: 1 | E44: NO | F44: URSULA RAMIRES | G44: URAMIRES | H44: 4CE7392HLV | I44: DT4CE7392HLV | J44: HP | K44: 280 G2 SFF BUSINESS | L44: 2 NORTE 798 | M44: 1 | N44: TALCA | O44: MAULE | P44: TALCA | Q44: ATENCIÓN COMERCIAL | R44: NO | S44: Funciona correctamente | T44: INTERNO | W44: https://drive.google.com/open?id=1Qx2TGt_gSO7NQ8tyBDRUWhjmAV9uaZ-6
A45: 210000008357-0000 | B45: NO TIENE | C45: TELEFONO IP | D45: 1 | E45: SI | F45: VALESKA CONSUELO MATURANA MATURANA | G45: N/A | H45: FCH131381AE | I45: N/A | J45: CISCO | K45: IP PHONE 7942 | L45: 2 NORTE 798 | M45: 1 | N45: TALCA | O45: MAULE | P45: TALCA | Q45: ATENCIÓN COMERCIAL | R45: N/A | T45: INTERNO | W45: https://drive.google.com/open?id=1Iljx2aaMMEf_uxMDHqzTASCnIIX3Gf3N
A46: 210000026315-0000 | B46: NO TIENE | C46: DESKTOP | D46: 1 | E46: NO | F46: VALESKA CONSUELO MATURANA MATURANA | G46: VCMATURANAM | H46: MXL1280W2S | I46: DT-MXL1280W2S | J46: HP | K46: NO VISIBLE | L46: 2 NORTE 798 | M46: 1 | N46: TALCA | O46: MAULE | P46: TALCA | Q46: ATENCIÓN COMERCIAL | R46: N/A | T46: INTERNO | W46: https://drive.google.com/open?id=1P4mjoRQLt5vEUPX2P9s2ryJ6TKt7u4tM
A47: 210000028698-0000 | B47: CGE007335 | C47: MONITOR | D47: 1 | E47: SI | F47: VALESKA MATURANA | G47: VCMATURANAM | H47: CNC122NVPX | I47: NO APLICA | J47: HP | K47: HP COMPAQ LE1711 | L47: 2 NORTE 798 | M47: 1 | N47: TALCA | O47: MAULE | P47: TALCA | Q47: ATENCIÓN COMERCIAL | R47: N/A | S47: Funciona correctamente | T47: INTERNO | W47: https://drive.google.com/open?id=1Q1Yaf4SN1fOBjQAg5vp2buX_cWPc5w1r
A48: 210000063744-0000 | B48: CGE005416 | C48: DESKTOP | D48: 1 | E48: NO | F48: VERONICA ASALGADO | G48: VASALGADO | H48: D17S003 | I48: DTD17S003 | J48: DELL | K48: D17S | L48: 2 NORTE 798 | M48: 1 | N48: TALCA | O48: MAULE | P48: TALCA | Q48: ATENCIÓN COMERCIAL | R48: NO | S48: Funciona correctamente | T48: INTERNO | W48: https://drive.google.com/open?id=1WVeTn9RbChJSX7Mj95rIYGM5VUb-CJFN
A49: 210000017960-0000 | B49: CGE001174 | C49: MONITOR | D49: 1 | F49: CARLOS FRANCISCO AGUIRRE PAEZ | G49: CFAGUIRREP | H49: CN0N300H641809BF1T4L | J49: DELL | K49: E1709WC | L49: 21 DE MAYO N° 1198 | M49: 1 | N49: TOCOPILLA | O49: ANTOFAGASTA | P49: TOCOPILLA | Q49: SUPERVISOR ACTIVO GLOBAL | S49: CARLOS FRANCISCO AGUIRRE PAEZ | T49: INTERNO | W49: =SUBTOTAL(9,A49:V49) -> 0
A50: 210000049590-0000 | B50: CGE011529 | C50: MONITOR | D50: 1 | F50: CARLOS FRANCISCO AGUIRRE PAEZ | G50: CFAGUIRREP | H50: 4CE739HQ9 | J50: HP | K50: 280 G2 | L50: 21 DE MAYO N° 1198 | M50: 1 | N50: TOCOPILLA | O50: ANTOFAGASTA | P50: TOCOPILLA | Q50: SUPERVISOR ACTIVO GLOBAL | S50: CARLOS FRANCISCO AGUIRRE PAEZ | T50: INTERNO | V50: EQUIPO SIN USO | W50: =SUBTOTAL(9,A50:V50) -> 0
A51: 210000016247-0000 | B51: CGE011531 | C51: MONITOR | D51: 1 | F51: CARLOS FRANCISCO AGUIRRE PAEZ | G51: CFAGUIRREP | H51: CN0X706H728729BL05LL | J51: DELL | K51: E1709WF | L51: 21 DE MAYO N° 1198 | M51: 1 | N51: TOCOPILLA | O51: ANTOFAGASTA | P51: TOCOPILLA | Q51: SUPERVISOR ACTIVO GLOBAL | S51: CARLOS FRANCISCO AGUIRRE PAEZ | T51: INTERNO | W51: =SUBTOTAL(9,A51:V51) -> 0
A52: 210000017964-0000 | B52: CGE011552 | C52: MONITOR | D52: 1 | F52: CARLOS FRANCISCO AGUIRRE PAEZ | G52: CFAGUIRREP | H52: CN0N300H641809BL1WFL | J52: DELL | K52: E1709WC | L52: 21 DE MAYO N° 1198 | M52: 1 | N52: TOCOPILLA | O52: ANTOFAGASTA | P52: TOCOPILLA | Q52: SUPERVISOR ACTIVO GLOBAL | S52: CARLOS FRANCISCO AGUIRRE PAEZ | T52: INTERNO | W52: =SUBTOTAL(9,A52:V52) -> 0
A53: 210000030273-0000 | B53: CGE008753 | C53: NOTEBOOK | D53: 1 | E53: SI | F53: CARLOS FRANCISCO AGUIRRE PAEZ (TOCOPILLA) | G53: CFAGUIRREP | H53: PF1CSW5L | I53: NBPF1CSW5L | J53: LENOVO | K53: THINKPAD L490 | L53: 21 DE MAYO N° 1198 | M53: 1 | N53: TOCOPILLA | O53: ANTOFAGASTA | P53: TOCOPILLA | Q53: SUPERVISOR ACTIVO GLOBAL | S53: CARLOS FRANCISCO AGUIRRE PAEZ (TOCOPILLA) | T53: INTERNO | W53: =SUBTOTAL(9,A53:V53) -> 0
A54: 210000016473-0000 | B54: CGE001176 | C54: MONITOR | D54: 1 | F54: JUAN EMILIO MUÑOZ CASTILLO | H54: CN0X706H728729BL2P4L | J54: DELL | K54: E1709WF | L54: 21 DE MAYO N° 1198 | M54: 1 | N54: TOCOPILLA | O54: ANTOFAGASTA | P54: TOCOPILLA | Q54: SUPERVISOR GLOBAL | S54: JUAN EMILIO MUÑOZ CASTILLO | T54: INTERNO | W54: =SUBTOTAL(9,A54:V54) -> 0
A55: 210000061615-0000 | B55: CGE001178 | C55: NOTEBOOK | D55: 1 | E55: SI | F55: JUAN EMILIO MUÑOZ CASTILLO | G55: JEMUNOZC | H55: 5CD207HD8S | I55: NB5CD207HD8S-1 | J55: HP | K55: PROBOOK 440 G8 | L55: 21 DE MAYO N° 1198 | M55: 1 | N55: TOCOPILLA | O55: ANTOFAGASTA | P55: TOCOPILLA | Q55: SUPERVISOR GLOBAL | S55: JUAN EMILIO MUÑOZ CASTILLO | T55: INTERNO | W55: =SUBTOTAL(9,A55:V55) -> 0
A56: 210000052267-0000 | B56: CGE001172 | C56: DESKTOP | D56: 1 | E56: SI | F56: MARGORIET XIMENA RAMIREZ ROJAS | G56: MXRAMIREZR | H56: 4CE7392J0V | I56: DT4CE739J0V-01 | J56: HP | K56: 280 G2 | L56: 21 DE MAYO N° 1198 | M56: 1 | N56: TOCOPILLA | O56: ANTOFAGASTA | P56: TOCOPILLA | Q56: EJECUTIVO EN ATENCIÓN AL CLIENTE | S56: MARGORIET XIMENA RAMIREZ ROJAS | T56: EXTERNO | W56: =SUBTOTAL(9,A56:V56) -> 0
A57: 210000015001-0000 | B57: CGE001171 | C57: MONITOR | D57: 1 | F57: MARGORIET XIMENA RAMIREZ ROJAS | H57: CNOX706H728729BL05HL | J57: DELL | K57: E1709WF | L57: 21 DE MAYO N° 1198 | M57: 1 | N57: TOCOPILLA | O57: ANTOFAGASTA | P57: TOCOPILLA | Q57: EJECUTIVO EN ATENCIÓN AL CLIENTE | S57: MARGORIET XIMENA RAMIREZ ROJAS | T57: EXTERNO | W57: =SUBTOTAL(9,A57:V57) -> 0
A58: 210000018108-0000 | B58: CGE011532 | C58: DOCKING | D58: 1 | E58: SI | F58: SOPORTE NI | H58: CN0CY640129619B76103A03 | J58: DELL | K58: PR02X | L58: 21 DE MAYO N° 1198 | M58: 1 | N58: TOCOPILLA | O58: ANTOFAGASTA | P58: TOCOPILLA | S58: SOPORTENI | T58: INTERNO | V58: SIN USUARIO | W58: =SUBTOTAL(9,A58:V58) -> 0
A59: 210000017683-0000 | B59: CGE011550 | C59: DESKTOP | D59: 1 | E59: SI | F59: SOPORTE NI | H59: 1TSXLL1 | I59: DT1TSXLL1 | J59: DELL | K59: LATITUDE E5500 | L59: 21 DE MAYO N° 1198 | M59: 1 | N59: TOCOPILLA | O59: ANTOFAGASTA | P59: TOCOPILLA | S59: SOPORTENI | T59: INTERNO | V59: SIN USUARIO | W59: =SUBTOTAL(9,A59:V59) -> 0
A60: 210000017975-0000 | B60: CGE011551 | C60: MONITOR | D60: 1 | E60: SI | F60: SOPORTE NI | H60: CN0N300H641809BF1VSL | J60: DELL | K60: E1709WC | L60: 21 DE MAYO N° 1198 | M60: 1 | N60: TOCOPILLA | O60: ANTOFAGASTA | P60: TOCOPILLA | S60: SOPORTENI | T60: INTERNO | V60: SIN USUARIO | W60: =SUBTOTAL(9,A60:V60) -> 0
A61: S/AF | B61: CGE011553 | C61: MONITOR | D61: 1 | E61: SI | F61: SOPORTE NI | H61: 803NDWECE873 | J61: LG | K61: L177WSBS | L61: 21 DE MAYO N° 1198 | M61: 1 | N61: TOCOPILLA | O61: ANTOFAGASTA | P61: TOCOPILLA | S61: SOPORTENI | T61: INTERNO | V61: SIN USO Y SIN USUARIO | W61: =SUBTOTAL(9,A61:V61) -> 0
A62: 210000017760-0000 | B62: CGE011554 | C62: DESKTOP | D62: 1 | E62: NO | F62: SOPORTE NI | H62: 2YFVML1 | I62: DT2YFVML1 | J62: DELL | K62: OPTIPLEX 380 | L62: 21 DE MAYO N° 1198 | M62: 1 | N62: TOCOPILLA | O62: ANTOFAGASTA | P62: TOCOPILLA | S62: SOPORTENI | T62: INTERNO | V62: SIN USO Y SIN USUARIO | W62: =SUBTOTAL(9,A62:V62) -> 0
A63: 210000036504-0000 | B63: CGE011580 | C63: DESKTOP | D63: 1 | E63: SI | F63: SOPORTE NI | H63: MXL13613L1 | I63: DTMXL13613L1 | J63: HP | K63: COMPAQ 8200 ELITE SMALL | L63: 21 DE MAYO N° 1198 | M63: 1 | N63: TOCOPILLA | O63: ANTOFAGASTA | P63: TOCOPILLA | S63: SOPORTENI | T63: INTERNO | V63: SIN USUARIO | W63: =SUBTOTAL(9,A63:V63) -> 0
A64: 210000016250-0000 | B64: CGE011581 | C64: MONITOR | D64: 1 | E64: SI | F64: SOPORTE NI | H64: CN0X706H728729BL061L | J64: DELL | K64: E1709WF | L64: 21 DE MAYO N° 1198 | M64: 1 | N64: TOCOPILLA | O64: ANTOFAGASTA | P64: TOCOPILLA | S64: SOPORTENI | T64: INTERNO | V64: SIN USUARIO | W64: =SUBTOTAL(9,A64:V64) -> 0
A65: 210000015004-0000 | B65: CGE001582 | C65: MONITOR | D65: 1 | E65: SI | F65: SOPORTE NI | H65: CN0X706H728729BL05RL | J65: DELL | K65: E1709WF | L65: 21 DE MAYO N° 1198 | M65: 1 | N65: TOCOPILLA | O65: ANTOFAGASTA | P65: TOCOPILLA | S65: SOPORTENI | T65: INTERNO | V65: SIN USO Y SIN USUARIO | W65: =SUBTOTAL(9,A65:V65) -> 0
A66: 210000052268-0000 | B66: CGE001173 | C66: DESKTOP | D66: 1 | E66: NO | F66: VERONICA ERNESTINA MOYA PIZARRO | G66: EJECUTIVOVEMP | H66: 4CE739HV6 | I66: DT4CE739HV66 | J66: HP | K66: 280 G2 | L66: 21 DE MAYO N° 1198 | M66: 1 | N66: TOCOPILLA | O66: ANTOFAGASTA | P66: TOCOPILLA | Q66: EJECUTIVO EN ATENCIÓN AL CLIENTE | S66: VERONICA ERNESTINA MOYA PIZARRO | T66: EXTERNO | W66: =SUBTOTAL(9,A66:V66) -> 0
A67: 210000016752-0000 | B67: CGE001170 | C67: MONITOR | D67: 1 | F67: VERONICA ERNESTINA MOYA PIZARRO | H67: CN0N300H6418002J0K8L | J67: DELL | K67: E1709WF | L67: 21 DE MAYO N° 1198 | M67: 1 | N67: TOCOPILLA | O67: ANTOFAGASTA | P67: TOCOPILLA | Q67: EJECUTIVO EN ATENCIÓN AL CLIENTE | S67: VERONICA ERNESTINA MOYA PIZARRO | T67: EXTERNO | W67: =SUBTOTAL(9,A67:V67) -> 0
A68: 210000027237-0000 | B68: CGE011816 | C68: MONITOR | D68: 1 | E68: SI | F68: CARLA LEON BASAURE | G68: EJECUTIVOCPLB | H68: CNC118QS60 | I68: NO TIENE | J68: HP | K68: COMPAQ LE1711 | L68: 3 ORIENTE 1331 LOCAL 3 EDIFICIO BOULEVARD DEL SOL | M68: 1 | N68: VIÑA DEL MAR | O68: VALPARAISO | P68: VIÑA DEL MAR | Q68: ATENCIÓN COMERCIAL | R68: NO | S68: CARLA LEON BASAURE | T68: INTERNO | U68: SE COLOCA ETIQUETA ENTEL | W68: =SUBTOTAL(9,A68:V68) -> 0
A69: 210000049521-0000 | B69: CGE008525 | C69: DESKTOP | D69: 1 | E69: SI | F69: CARLA LEON BASAURE | G69: EJECUTIVOCPLB | H69: 4CE7392HXM | I69: DT4CE7392HXM | J69: HP | K69: PC HP 280 G2 | L69: 3 ORIENTE 1331 LOCAL 3 EDIFICIO BOULEVARD DEL SOL | M69: 1 | N69: VIÑA DEL MAR | O69: VALPARAISO | P69: VIÑA DEL MAR | Q69: ATENCIÓN COMERCIAL | R69: NO | S69: CARLA LEON BASAURE | T69: INTERNO | V69: USUARIA A CARGO DE DOS EQUIPOS | W69: =SUBTOTAL(9,A69:V69) -> 0
A70: 210000023189-0000 | B70: CGE008526 | C70: MONITOR | D70: 1 | E70: SI | F70: CARLA LEON BASAURE | G70: EJECUTIVOCPLB | H70: CNON300H64180OCF008L | I70: NO TIENE | J70: DELL | K70: E1709W | L70: 3 ORIENTE 1331 LOCAL 3 EDIFICIO BOULEVARD DEL SOL | M70: 1 | N70: VIÑA DEL MAR | O70: VALPARAISO | P70: VIÑA DEL MAR | Q70: ATENCIÓN COMERCIAL | R70: NO | S70: CARLA LEON BASAURE | T70: INTERNO | V70: USUARIA A CARGO DE DOS EQUIPOS | W70: =SUBTOTAL(9,A70:V70) -> 0
A71: 210000033430-0000 | B71: CGE008521 | C71: DESKTOP | D71: 1 | E71: NO | F71: CARLA LEON BASAURE | G71: EJECUTIVOCPLB | H71: MXL13613L9 | I71: DTMXL13613L91 | J71: HP | K71: COMPAQ8200 ELITE SFF PC INTEL CORE I3 -2100 | L71: 3 ORIENTE 1331 LOCAL 3 EDIFICIO BOULEVARD DEL SOL | M71: 1 | N71: VIÑA DEL MAR | O71: VALPARAISO | P71: VIÑA DEL MAR | Q71: ATENCIÓN COMERCIAL | R71: NO | S71: CARLA LEON BASAURE | T71: INTERNO | W71: =SUBTOTAL(9,A71:V71) -> 0
A72: 210000027236-0000 | B72: CGE008531 | C72: MONITOR | D72: 1 | E72: SI | F72: CLAUDIA SUAREZ GONZALEZ | G72: EJECUTIVOCASG | H72: CNC118QS0 | I72: NO TIENE | J72: HP | K72: COMPAQ LE1711 | L72: 3 ORIENTE 1331 LOCAL 3 EDIFICIO BOULEVARD DEL SOL | M72: 1 | N72: VIÑA DEL MAR | O72: VALPARAISO | P72: VIÑA DEL MAR | Q72: ATENCIÓN COMERCIAL | R72: NO | S72: CLAUDIA SUAREZ GONZALEZ | T72: INTERNO | W72: =SUBTOTAL(9,A72:V72) -> 0
A73: 210000065839-0000 | B73: CGE010033 | C73: DESKTOP | D73: 1 | E73: SI | F73: EMA BARRAZA VARGAS | G73: EJECUTIVOAT_EBV | H73: MP2ASYGG | I73: DTMP2ASYGG | J73: LENOVO | K73: THINK CENTRE 12K9003XLS INTEL CORE I7-13700H | L73: 3 ORIENTE 1331 LOCAL 3 EDIFICIO BOULEVARD DEL SOL | M73: 1 | N73: VIÑA DEL MAR | O73: VALPARAISO | P73: VIÑA DEL MAR | Q73: ATENCIÓN COMERCIAL | R73: NO | S73: EMA BARRAZA VARGAS | T73: INTERNO | W73: =SUBTOTAL(9,A73:V73) -> 0
A74: 210000028086-0000 | B74: CGE008532 | C74: DESKTOP | D74: 1 | E74: SI | F74: FABIOLA JULIETTE ACUÑA GARRIDO EXT | G74: EJECUTIVOCASG | H74: MXL1480HGY | I74: DTMXL1480HGY | J74: HP | K74: COMPAQ8200 ELITE SFF PC INTEL CORE I3 -2100 | L74: 3 ORIENTE 1331 LOCAL 3 EDIFICIO BOULEVARD DEL SOL | M74: 1 | N74: VIÑA DEL MAR | O74: VALPARAISO | P74: VIÑA DEL MAR | Q74: ATENCIÓN COMERCIAL | R74: NO | S74: CLAUDIA SUAREZ GONZALEZ | T74: INTERNO | W74: =SUBTOTAL(9,A74:V74) -> 0
A75: 210000026581-0000 | B75: CGE011815 | C75: MONITOR | D75: 1 | E75: SI | F75: NOEMI MARLEN CEBALLOS PAILLAN | G75: EJECUTIVONCP | H75: CNC115PQRX | I75: NO TIENE | J75: HP | K75: COMPAQLE1711 | L75: 3 ORIENTE 1331 LOCAL 3 EDIFICIO BOULEVARD DEL SOL | M75: 1 | N75: VIÑA DEL MAR | O75: VALPARAISO | P75: VIÑA DEL MAR | Q75: ATENCIÓN COMERCIAL | R75: NO | S75: NOEMI CEBALLOS PAILLAN | T75: INTERNO | U75: SE COLOCA ETIQUETA ENTEL | W75: =SUBTOTAL(9,A75:V75) -> 0
A76: S/AF | B76: CGE008523 | C76: DESKTOP | D76: 1 | E76: SI | F76: NOEMI MARLEN CEBALLOS PAILLAN | G76: EJECUTIVONCP | H76: MJ0EJYZS | I76: NBMJ0EJYZS | J76: LENOVO | K76: THINKCENTRE 11DBS5U800 INTEL CORE I5 -10500 | L76: 3 ORIENTE 1331 LOCAL 3 EDIFICIO BOULEVARD DEL SOL | M76: 1 | N76: VIÑA DEL MAR | O76: VALPARAISO | P76: VIÑA DEL MAR | Q76: ATENCIÓN COMERCIAL | R76: NO | S76: NOEMI CEBALLOS PAILLAN | T76: INTERNO | W76: =SUBTOTAL(9,A76:V76) -> 0
A77: 210000058844-0000 | B77: CGE003965 | C77: NOTEBOOK | D77: 1 | E77: NO | F77: ABELINO SEGUNDO ANTIAS CERDA | G77: ASANTIASC | H77: R90YBTKH | I77: NBR90YBTKH | J77: LENOVO | K77: THINKPAD | L77: 3 PUENTES | M77: 1 | N77: PUNTA ARENAS | O77: MAGALLANES | P77: PUNTA ARENAS | Q77: Vigilancia | R77: NO | S77: ABELINO SEGUNDO ANTIAS CERDA | T77: INTERNO | X77: https://drive.google.com/open?id=159-vgHICqyas8aDbrXCwhluslGIg6PHu
A78: 210000063960-0000 | B78: CGE005364 | C78: MONITOR | D78: 1 | E78: NO | F78: ALDO DOMINGO GHISONI HUTT | G78: ADGHISONIH | H78: 9RNDLW2 | J78: DELL | K78: P2422H | L78: 3 PUENTES | M78: 1 | N78: PUNTA ARENAS | O78: MAGALLANES | P78: PUNTA ARENAS | Q78: Central 3 ptes | R78: NO | S78: ALDO DOMINGO GHISONI HUTT | T78: INTERNO | X78: https://drive.google.com/open?id=1X4t2GErThybHvLQ1ReqEcD7IkVBKadOx
A79: 210000030285-0000 | B79: CGE001928 | C79: NOTEBOOK | D79: 1 | E79: NO | F79: ALDO DOMINGO GHISONI HUTT | G79: ADGHISONIH | H79: PF1WA30B | I79: NBPF1WA30B | J79: LENOVO | K79: THINKPAD | L79: 3 PUENTES | M79: 1 | N79: PUNTA ARENAS | O79: MAGALLANES | P79: PUNTA ARENAS | Q79: Central 3 ptes | R79: NO | S79: ALDO DOMINGO GHISONI HUTT | T79: INTERNO | X79: https://drive.google.com/open?id=11udeT8jV_Ik-JGQWFIgTu1c8QRdr80dz
A80: S/AF | B80: CGE001909 | C80: NOTEBOOK | D80: 1 | E80: NO | F80: CRISTIAN FRANCISCO MADRID CANALEA | G80: CFMADRIDC | H80: 5CG70142 | I80: Nb-5CG70142-FR | J80: HP | K80: ELITEBOOK 840 | L80: 3 PUENTES | M80: 1 | N80: PUNTA ARENAS | O80: MAGALLANES | P80: PUNTA ARENAS | Q80: Central 3 ptea | R80: SI | S80: CRISTIAN FRANCISCO MADRID CANALEA | T80: INTERNO
A81: 210000063973-0000 | B81: CGE005372 | C81: MONITOR | D81: 1 | E81: NO | F81: CRISTIAN FRANCISCO MADRID CANALES | G81: CFMADRIDC | H81: 6NPGTX4 | J81: DELL | K81: P2422H | L81: 3 PUENTES | M81: 1 | N81: PUNTA ARENAS | O81: MAGALLANES | P81: PUNTA ARENAS | Q81: Central 3 ptes | R81: NO | S81: CRISTIAN FRANCISCO MADRID CANALES | T81: INTERNO | X81: https://drive.google.com/open?id=1zrQjha4J3bbc9hE8LL9mBG_yfreKLj7l
A82: S/AF | B82: CGE004218 | C82: NOTEBOOK | D82: 1 | E82: NO | F82: DIEGO FABIAN HIJERRA HERNANDEZ | G82: DHIJERRAH | H82: 5CD30855GZ | I82: NB5CD30855GZ | J82: HP | K82: PROBOOK 440 | L82: 3 PUENTES | M82: 1 | N82: PUNTA ARENAS | O82: MAGALLANES | P82: PUNTA ARENAS | Q82: Central 3 ptes | R82: NO | S82: DIEGO FABIAN HIJERRA HERNANDEZ | T82: INTERNO
A83: 210000063936-0000 | B83: CGE005373 | C83: MONITOR | D83: 1 | E83: NO | F83: FABIAN FERNANDO CARDENAS PAREDES | G83: FFCARDENASP | H83: 7TQJSM1 | J83: DELL | K83: P2422H | L83: 3 PUENTES | M83: 1 | N83: PUNTA ARENAS | O83: Magallanes | P83: PUNTA ARENAS | Q83: Central 3 ptes | R83: NO | S83: FABIAN FERNANDO CARDENAS PAREDES | T83: INTERNO | X83: https://drive.google.com/open?id=1xWedytPgLcZ99o7XGGhIEiWJnxZd3XLn
A84: S/AF | B84: CGE005111 | C84: NOTEBOOK | D84: 1 | E84: NO | F84: FABIAN FERNANDO CARDENAS PAREDES | G84: FFCARDENASP | H84: GKJ89W3 | I84: NBGKJ89W3 | J84: DELL | K84: LATITUDE 5440 | L84: 3 PUENTES | M84: 1 | N84: PUNTA ARENAS | O84: Magallanes | P84: PUNTA ARENAS | Q84: Central 3 ptes | R84: NO | S84: FABIAN FERNANDO CARDENAS PAREDES | T84: INTERNO
A85: 210000063040-0000 | B85: CGE004171 | C85: NOTEBOOK | D85: 1 | E85: NO | F85: FERNANDO JAVIER VARGAS ALVARADO | G85: FJVARGASA | H85: 5CD30855N6 | I85: NB5CD30855N6 | J85: HP | K85: PROBOOK 440 | L85: 3 PUENTES | M85: 1 | N85: PUNTA ARENAS | O85: MAGALLANES | P85: PUNTA ARENAS | Q85: Central 3 ptes | R85: SI | S85: FERNANDO JAVIER VARGAS ALVARADO | T85: INTERNO | X85: https://drive.google.com/open?id=1cYdeUOm-0PAu0dOOrC2xg7zAnRJce5IW
A86: S/AF | B86: CGE005459 | C86: NOTEBOOK | D86: 1 | E86: NO | F86: FRANCISCA ALEJANDRA TORRES GU | G86: FTORRESG | H86: 4XS79W3 | I86: NB4XS79W3 | J86: DELL | K86: LATITUDE 5440 | L86: 3 PUENTES | M86: 1 | N86: PUNTA ARENAS | O86: MAGALLANES | P86: PUNTA ARENAS | Q86: Central 3 ptes | R86: NO | S86: FRANCISCA ALEJANDRA TORRES GU | T86: INTERNO
A87: S/AF | B87: CGE001864 | C87: NOTEBOOK | D87: 1 | E87: NO | F87: FRANCISCO JAVIER CHAMIA MUÑOZ | G87: FJCHAMIAM | H87: R9117545 | I87: NBR9117545 | J87: LENOVO | K87: THINKPAD | L87: 3 PUENTES | M87: 1 | N87: PUNTA ARENAS | O87: MAGALLANES | P87: PUNTA ARENAS | Q87: Central 3 ptes | R87: NO | S87: FRANCISCO JAVIER CHAMIA MUÑOZ | T87: INTERNO
A88: 210000063937-0000 | B88: CGE005365 | C88: MONITOR | D88: 1 | E88: NO | F88: FRANCISCO JAVIER CHAMIANMUÑOZ | G88: FJCHAMIAM | H88: 3KMXQT7 | J88: DELL | K88: P2422H | L88: 3 PUENTES | M88: 1 | N88: PUNTA ARENAS | O88: MAGALLANES | P88: PUNTA ARENAS | Q88: Central 3 ptes | R88: NO | S88: FRANCISCO JAVIER CHAMIANMUÑOZ | T88: INTERNO | X88: https://drive.google.com/open?id=1wHbfPBObwGdh2i1VqeLuz0-7cPuZXLDd
A89: 210000063927-0000 | B89: CGE005371 | C89: MONITOR | D89: 1 | E89: NO | F89: HECTOR EDUARDO SOTO MIHOVILOVIC | G89: HESOTOM | H89: 2VPLCY6 | J89: DELL | K89: P2422H | L89: 3 PUENTES | M89: 1 | N89: PUNTA ARENAS | O89: MAGALLANES | P89: PUNTA ARENAS | Q89: Central 3 ptes | R89: NO | S89: HECTOR EDUARDO SOTO MIHOVILOVIC | T89: INTERNO | X89: https://drive.google.com/open?id=1uImmyFKobGLgXQa4H1FjKo_IuUyLpW7e
A90: 210000045937-0000 | B90: CGE001923 | C90: NOTEBOOK | D90: 1 | E90: NO | F90: HECTOR EDUARDO SOTO MIHOVILOVIC | G90: HESOTOM | H90: 5CG6411Z1S | I90: NB5CG6411Z1S | J90: HP | K90: ELITEBOOK 840 | L90: 3 PUENTES | M90: 1 | N90: PUNTA ARENAS | O90: MAGALLANES | P90: PUNTA ARENAS | Q90: Central 3 ptes | R90: NO | S90: HECTOR EDUARDO SOTO MIHOVILOVIC | T90: INTERNO | X90: https://drive.google.com/open?id=1HFx7DtArorkxR4EPT9Syp7-hMQ9qodEO
A91: 210000047295-0000 | B91: CGE008893 | C91: NOTEBOOK | D91: 1 | E91: NO | F91: JAIME LESLY ANTIÑIRRE HESS | G91: JLANTIRRINEH | H91: 5CG70141YF | I91: NB5CG70141YF | J91: HP | K91: ELITEBOOK 840 | L91: 3 PUENTES | M91: 1 | N91: PUNTA ARENAS | O91: MAGALLANES | P91: PUNTA ARENAS | Q91: Taller mecanico | R91: NO | S91: JAIME LESLY ANTIÑIRRE HESS | T91: INTERNO | X91: https://drive.google.com/open?id=1r3KUipyrUCFW4GOEApsG-r57Wtc_akzf
A92: S/AF | B92: CGE008890 | C92: MONITOR | D92: 1 | E92: NO | F92: JOSELYN SILVANA TAPIA PANICHINE | G92: JTAPIAP | H92: 4XWKRN9 | J92: DELL | K92: P2314HT | L92: 3 PUENTES | M92: 1 | N92: PUNTA ARENAS | O92: MAGALLANES | P92: PUNTA ARENAS | Q92: Central 3 ptes | R92: NO | S92: JOSELYN SILVANA TAPIA PANICHINE | T92: INTERNO
A93: 210000063956-0000 | B93: CGE005369 | C93: MONITOR | D93: 1 | E93: NO | F93: JOSELYN SILVANA TAPIA PANICHINI | G93: JTAPIAP | H93: 8BLDVE3 | J93: DELL | K93: P2422H | L93: 3 PUENTES | M93: 1 | N93: PUNTA ARENAS | O93: MAGALLANES | P93: PUNTA ARENAS | Q93: Central 3 ptes | R93: NO | S93: JOSELYN SILVANA TAPIA PANICHINI | T93: INTERNO | X93: https://drive.google.com/open?id=1Kt_Wo95xPgZy8iCaeUA7orEna_L0wVqi
A94: S/AF | B94: CGE004240 | C94: NOTEBOOK | D94: 1 | E94: NO | F94: JOSELYN SILVANA TAPIA PANICHINI | G94: JTAPIAP | H94: 5CD308C14W | I94: NB5CD308C14W | J94: HP | K94: ELITEBOOK 640 | L94: 3 PUENTES | M94: 1 | N94: PUNTA ARENAS | O94: MAGALLANES | P94: PUNTA ARENAS | Q94: Central 3 ptes | R94: NO | S94: JOSELYN SILVANA TAPIA PANICHINI | T94: INTERNO
A95: 210000041928-0000 | B95: CGE008896 | C95: NOTEBOOK | D95: 1 | E95: NO | F95: JUAN CARLOS CAVALLIERI PEÑA | G95: ELECTRICISTAJCP | H95: 5CG6011VX7 | I95: NB5CG6011VX7 | J95: HP | K95: ELITEBOOK 840 | L95: 3 PUENTES | M95: 1 | N95: PUNTA ARENAS | O95: MAGALLANES | P95: PUNTA ARENAS | Q95: Taller electrico | R95: NO | S95: JUAN CARLOS CAVALLIERI PEÑA | T95: INTERNO | X95: https://drive.google.com/open?id=1O-fXT8WL6tcksr0bgjnwew0EfMTq1Kza
A96: 210000063966-0000 | B96: CGE005377 | C96: MONITOR | D96: 1 | E96: NO | F96: JUAN CARLOS TORRES MUÑOZ | G96: JCTORRES | H96: 5SZFVQ7 | J96: DELL | K96: P2421H | L96: 3 PUENTES | M96: 1 | N96: PUNTA ARENAS | O96: MAGALLANES | P96: PUNTA ARENAS | Q96: Taller mantenimiento | R96: NO | S96: JUAN CARLOS TORRES MUÑOZ | T96: INTERNO | X96: https://drive.google.com/open?id=1c8uGQdng4X40vdin8c9mFzx_Mt-xp_Vj
A97: 210000063586-0000 | B97: CGE005566 | C97: NOTEBOOK | D97: 1 | E97: NO | F97: JUAN FRANCISCO ALVARADO ASTUDILLO | G97: JFALVARADOA | H97: 5ĶL99W3 | I97: NB5ĶL99W3 | J97: DELL | K97: LATITUDE 5440 | L97: 3 PUENTES | M97: 1 | N97: PUNTA ARENAS | O97: MAGALLANES | P97: PUNTA ARENAS | Q97: Central 3 ptes | R97: NO | S97: JUAN FRANCISCO ALVARADO ASTUDILLO | T97: INTERNO | X97: https://drive.google.com/open?id=1xmYD0wyAyH_8oZycjh8t1SMBoCc9tieh
A98: 210000063758-0000 | B98: CGE005433 | C98: DESKTOP | D98: 1 | E98: NO | F98: JUAN MACHUCA | G98: JFMACHUCAG | H98: C4NZ704 | I98: DTC4NZ704 | J98: DELL | K98: OPTIPLEX | L98: 3 PUENTES | M98: 1 | N98: PUNTA ARENAS | O98: MAGALLANES | P98: PUNTA ARENAS | Q98: Vigilancia | R98: NO | S98: JUAN MACHUCA | T98: INTERNO | X98: https://drive.google.com/open?id=1H7bglN6xznjpqZnvfS0h3KVMo95O1niH
A99: 210000023187-0000 | B99: CGE001917 | C99: MONITOR | D99: 1 | E99: NO | F99: JUAN MACHUCA | G99: JFMACHUCAG | H99: 6JVBYP3 | J99: DELL | K99: E1709W | L99: 3 PUENTES | M99: 1 | N99: PUNTA ARENAS | O99: MAGALLANES | P99: PUNTA ARENAS | Q99: Vigilancia | R99: NO | S99: JUAN MACHUCA | T99: INTERNO | X99: https://drive.google.com/open?id=1qpEkPEHkK5Tf1vhVmOhtq9bDuhxQ5h-N
A100: S/AF | B100: CGE005076 | C100: NOTEBOOK | D100: 1 | E100: NO | F100: KAREN DANIELA GALLARDO WILIAMS | G100: KGALLARDOW | H100: 5CHB9W3 | I100: NB5CHB9W3 | K100: LATITUDE 5440 | L100: 3 PUENTES | M100: 1 | N100: PUNTA ARENAS | O100: MAGALLANES | P100: PUNTA ARENAS | Q100: Central 3 ptes | R100: SI | S100: KAREN DANIELA GALLARDO WILIAMS | T100: INTERNO
...

Sheet PILOTO
A1: Activo Fijo | B1: Rotulo Entel | C1: estado | D1: Tipo Dispositivo | E1: Unidades | F1: Teléfono | G1: Nombre de Usuario | H1: Usuario de RED | I1: Número de Serie | J1: Hostname | K1: Marca | L1: Modelo | M1: Dirección | N1: Piso | O1: Comuna | P1: Región | Q1: Ciudad | R1: Area | S1: Necesita Alzador | T1: Nombre de usuario Responsable | U1: Tipo Usuario | V1: Observaciones | W1: Observaciones 2
A2: 210000065975-0000 | B2: CG009091 | C2: =VLOOKUP(B2,CONSOLIDADO!$B$1:$B$722,2,FALSE) -> #N/A | D2: DESKTOP | E2: 1 | F2: SI | G2: RODRIGO GERMAN CORTES MARIN | H2: RGCORTESM | I2: 8CN3500B4W | J2: AIO8CN3500B4W | K2: HP | L2: PRO ONE 440 G9 | M2: PEDRO AGUIRRE CERDA 5558 | N2: 2 | O2: ANTOFAGASTA | P2: ANTOFAGASTA | Q2: ANTOFAGASTA | R2: DESPACHO DE OPERACIÓN | S2: SI | T2: RODRIGO GERMAN CORTES MARIN | U2: INTERNO
A3: 2100000029932-0000 | B3: CGE0000365 | C3: =VLOOKUP(B3,CONSOLIDADO!$B$1:$B$722,2,FALSE) -> #N/A | D3: NOTEBOOK | E3: 1 | F3: SI | G3: MARIA DE LOS ANGELES CONTRERAS MARQUEZ | H3: APOYOMACM | I3: PF221WQ0 | J3: NBPF221WQ0-02 | K3: LENOVO | L3: L490 G8 | M3: PEDRO AGUIRRE CERDA 5558 | N3: 2 | O3: ANTOFAGASTA | P3: ANTOFAGASTA | Q3: ANTOFAGASTA | R3: PROGRAMACIÓN | T3: MARIA DE LOS ANGELES CONTRERAS MARQUEZ | U3: INTERNO
A4: 210000062166-0000 | B4: CGE000096 | C4: =VLOOKUP(B4,CONSOLIDADO!$B$1:$B$722,2,FALSE) -> #N/A | D4: DESKTOP | E4: 1 | F4: SI | G4: OSCAR SEGOVIA COLLADO | I4: 4CE237DHB9 | J4: DT4CE237DHB9 | K4: HP | L4: PRO 400 G9 | M4: PEDRO AGUIRRE CERDA 5558 | N4: 2 | O4: ANTOFAGASTA | P4: ANTOFAGASTA | Q4: ANTOFAGASTA | R4: CGE TRANSMISIÓN | T4: OSCAR SEGOVIA COLLADO | U4: INTERNO
A5: 210000062551-0000 | B5: CGE000340 | C5: =VLOOKUP(B5,CONSOLIDADO!$B$1:$B$722,2,FALSE) -> #N/A | D5: NOTEBOOK | E5: 1 | F5: SI | G5: PATRICIO ALEJANDRO VELASQUEZ PARRA | H5: PAVELASQUEZP | I5: 6C5X6LT | J5: NB-5CD236FFXQ | K5: HP | L5: PROBOOK 440 G9 | M5: PEDRO AGUIRRE CERDA 5558 | N5: 2 | O5: ANTOFAGASTA | P5: ANTOFAGASTA | Q5: ANTOFAGASTA | R5: CGE TRANSMISIÓN | S5: NO | T5: PATRICIO ALEJANDRO VELASQUEZ PARRA | U5: INTERNO
A6: 21000025508-0000 | B6: CGE000341 | C6: =VLOOKUP(B6,CONSOLIDADO!$B$1:$B$722,2,FALSE) -> #N/A | D6: MONITOR | E6: 1 | F6: SI | G6: SOPORTENI | H6: N/A | I6: CNC115PRWQ | J6: N/A | K6: HP | L6: LE1711 | M6: PEDRO AGUIRRE CERDA 5558 | N6: 1 | O6: ANTOFAGASTA | P6: ANTOFAGASTA | Q6: ANTOFAGASTA | R6: DELEGACIÓN | T6: SOPORTENI | W6: SOPORTENI
A7: NO TIENE | B7: CGE000344 | C7: =VLOOKUP(B7,CONSOLIDADO!$B$1:$B$722,2,FALSE) -> #N/A | D7: MONITOR | E7: 1 | F7: SI | G7: MILKO HENRY SANCHEZ SALFATE | I7: CN0G8TVHQDC0005H791BA09 | K7: DELL | L7: P2419H | M7: PEDRO AGUIRRE CERDA 5558 | N7: 2 | O7: ANTOFAGASTA | P7: ANTOFAGASTA | Q7: ANTOFAGASTA | R7: DESPACHO DE OPERACIÓN | T7: MILKO HENRY SANCHEZ SALFATE | U7: INTERNO | W7: REVISAR POR CARINA GALLARDO
A8: 210000061086-0000 | B8: CGE000345 | C8: =VLOOKUP(B8,CONSOLIDADO!$B$1:$B$722,2,FALSE) -> #N/A | D8: NOTEBOOK | E8: 1 | F8: SI | G8: YURI LIZETH VALENCIA MURILLO | H8: PROGRAMADORYLVM | I8: 5CD207HF5Z | J8: NB5CD207HF5Z | K8: HP | L8: PROOBOOK 440 G8 | M8: PEDRO AGUIRRE CERDA 5558 | N8: 2 | O8: ANTOFAGASTA | P8: ANTOFAGASTA | Q8: ANTOFAGASTA | R8: PROGRAMACIÓN | T8: YURI LIZETH VALENCIA MURILLO | U8: INTERNO
A9: 210000028482-0000 | B9: CGE000346 | C9: =VLOOKUP(B9,CONSOLIDADO!$B$1:$B$722,2,FALSE) -> #N/A | D9: MONITOR | E9: 1 | F9: SI | G9: PRISCILA VILLARROEL VERGARA | H9: N/A | I9: CNC117018Z | J9: DTMXL6382D4V | K9: HP | L9: LE1711 | M9: PEDRO AGUIRRE CERDA 5558 | N9: 1 | O9: ANTOFAGASTA | P9: ANTOFAGASTA | Q9: ANTOFAGASTA | R9: COMERCIAL | T9: PRISCILA VILLARROEL VERGARA | U9: INTERNO | W9: PISO 1
A10: NO TIENE | B10: CGE000348 | C10: =VLOOKUP(B10,CONSOLIDADO!$B$1:$B$722,2,FALSE) -> #N/A | D10: MONITOR | E10: 1 | F10: SI | G10: PABLO IGNACIO TRIGO ARAYA | I10: CNOKHONGQDC008240NLA05 | K10: DELL | L10: P2417H | M10: PEDRO AGUIRRE CERDA 5558 | N10: 2 | O10: ANTOFAGASTA | P10: ANTOFAGASTA | Q10: ANTOFAGASTA | R10: DESPACHO DE OPERACIÓN | T10: PABLO IGNACIO TRIGO ARAYA | U10: INTERNO
A11: 6981 | B11: CGE000349 | C11: =VLOOKUP(B11,CONSOLIDADO!$B$1:$B$722,2,FALSE) -> #N/A | D11: DESKTOP | E11: 1 | F11: SI | G11: PRISCILA VILLARROEL VERGARA | H11: PVILLARROELV | I11: MXL6382D4V | J11: DTMXL6382D4V | K11: HP | L11: 400 G3 | M11: PEDRO AGUIRRE CERDA 5558 | N11: 1 | O11: ANTOFAGASTA | P11: ANTOFAGASTA | Q11: ANTOFAGASTA | R11: COMERCIAL | T11: PRISCILA VILLARROEL VERGARA | U11: INTERNO | W11: PISO 1
A12: NO TIENE | B12: CGE000351 | C12: =VLOOKUP(B12,CONSOLIDADO!$B$1:$B$722,2,FALSE) -> #N/A | D12: MONITOR | E12: 1 | F12: SI | G12: RODRIGO GERMAN CORTES MARIN | I12: CN0R9F1P742615CG52WS | K12: DELL | L12: U2414HB | M12: PEDRO AGUIRRE CERDA 5558 | N12: 2 | O12: ANTOFAGASTA | P12: ANTOFAGASTA | Q12: ANTOFAGASTA | R12: DESPACHO DE OPERACIÓN | T12: RODRIGO GERMAN CORTES MARIN | U12: INTERNO | W12: REVISAR POR CARINA GALLARDO
A13: 7004 | B13: CGE000357 | C13: =VLOOKUP(B13,CONSOLIDADO!$B$1:$B$722,2,FALSE) -> #N/A | D13: MONITOR | E13: 1 | F13: SI | G13: YURI LIZETH VALENCIA MURILLO | I13: CNORNMH674445OCFCRLS | K13: DELL | L13: P190ST | M13: PEDRO AGUIRRE CERDA 5558 | N13: 2 | O13: ANTOFAGASTA | P13: ANTOFAGASTA | Q13: ANTOFAGASTA | R13: PROGRAMACIÓN | T13: YURI LIZETH VALENCIA MURILLO | U13: INTERNO
A14: NO TIENE | B14: CGE000358 | C14: =VLOOKUP(B14,CONSOLIDADO!$B$1:$B$722,2,FALSE) -> #N/A | D14: MONITOR | E14: 1 | F14: SI | G14: YURI LIZETH VALENCIA MURILLO | I14: CN0RNMH6744450CFCJVS | K14: DELL | L14: P190ST | M14: PEDRO AGUIRRE CERDA 5558 | N14: 2 | O14: ANTOFAGASTA | P14: ANTOFAGASTA | Q14: ANTOFAGASTA | R14: PROGRAMACIÓN | T14: YURI LIZETH VALENCIA MURILLO | U14: INTERNO | W14: REVISAR POR CARINA GALLARDO
A15: 210000060031-0000 | B15: CGE000359 | C15: =VLOOKUP(B15,CONSOLIDADO!$B$1:$B$722,2,FALSE) -> #N/A | D15: NOTEBOOK | E15: 1 | F15: SI | G15: OSCAR MAURICIO VIDELA INOSTROZA | H15: OMVIDELAI | I15: MJ0EJZ0V | J15: NDMJ0EJZ0V | K15: LENOVO | L15: M70S | M15: PEDRO AGUIRRE CERDA 5558 | N15: 2 | O15: ANTOFAGASTA | P15: ANTOFAGASTA | Q15: ANTOFAGASTA | R15: DESPACHO DE OPERACIÓN | T15: OSCAR MAURICIO VIDELA INOSTROZA | U15: INTERNO
A16: 210000026729-0000 | B16: CGE000362 | C16: =VLOOKUP(B16,CONSOLIDADO!$B$1:$B$722,2,FALSE) -> #N/A | D16: MONITOR | E16: 1 | F16: SI | G16: CRISTIAN SAN MARTIN VILLAROEL | I16: CNC115PR29 | K16: HP | L16: COMPAQ LE1711 | M16: PEDRO AGUIRRE CERDA 5558 | N16: 2 | O16: ANTOFAGASTA | P16: ANTOFAGASTA | Q16: ANTOFAGASTA | R16: PROGRAMACIÓN | T16: CRISTIAN SAN MARTIN VILLAROEL | U16: INTERNO
A17: 210000028707-0000 | B17: CGE000363 | C17: =VLOOKUP(B17,CONSOLIDADO!$B$1:$B$722,2,FALSE) -> #N/A | D17: MONITOR | E17: 1 | F17: SI | G17: OSCAR MAURICIO VIDELA INOSTROZA | I17: CNC112QDZN | K17: HP | L17: LE1711 | M17: PEDRO AGUIRRE CERDA 5558 | N17: 2 | O17: ANTOFAGASTA | P17: ANTOFAGASTA | Q17: ANTOFAGASTA | R17: DESPACHO DE OPERACIÓN | T17: OSCAR MAURICIO VIDELA INOSTROZA | U17: INTERNO
A18: 210000016890-0000 | B18: CGE000368 | C18: =VLOOKUP(B18,CONSOLIDADO!$B$1:$B$722,2,FALSE) -> #N/A | D18: MONITOR | E18: 1 | F18: SI | G18: EZEQUIEL MURA MONSALVEZ | H18: APOYOEEMM | I18: CN0N445N7426101N28GU | K18: DELL | L18: E170SB | M18: PEDRO AGUIRRE CERDA 5558 | N18: 2 | O18: ANTOFAGASTA | P18: ANTOFAGASTA | Q18: ANTOFAGASTA | R18: PROGRAMACIÓN | T18: EZEQUIEL MURA MONSALVEZ | U18: INTERNO
A19: NO TIENE | B19: CGE000370 | C19: =VLOOKUP(B19,CONSOLIDADO!$B$1:$B$722,2,FALSE) -> #N/A | D19: DESKTOP | E19: 1 | F19: SI | G19: EZEQUIEL MURA MONSALVEZ | H19: APOYOEEMM | I19: MJ0EJZ29 | J19: NDMJ0EJZ29 | K19: LENOVO | L19: M70S | M19: PEDRO AGUIRRE CERDA 5558 | N19: 2 | O19: ANTOFAGASTA | P19: ANTOFAGASTA | Q19: ANTOFAGASTA | R19: PROGRAMACIÓN | T19: EZEQUIEL MURA MONSALVEZ | U19: INTERNO | W19: REVISAR POR CARINA GALLARDO
A20: 2100000026759-0000 | B20: CGE000373 | C20: =VLOOKUP(B20,CONSOLIDADO!$B$1:$B$722,2,FALSE) -> #N/A | D20: MONITOR | E20: 1 | F20: SI | G20: LUIS ALBERTO TAPIA CASTILLO | I20: CNC118QQQFQ | K20: HP | L20: LE1711 | M20: PEDRO AGUIRRE CERDA 5558 | N20: 1 | O20: ANTOFAGASTA | P20: ANTOFAGASTA | Q20: ANTOFAGASTA | R20: CORDINACION DE PROVEEDORES | T20: LUIS ALBERTO TAPIA CASTILLO | U20: INTERNO | W20: PISO 2
A21: 2100000-27377-0000 | B21: CGE000379 | C21: =VLOOKUP(B21,CONSOLIDADO!$B$1:$B$722,2,FALSE) -> #N/A | D21: MONITOR | E21: 1 | F21: NO | G21: DAYANA RAQUEL FUENTES CASTILLO | I21: CNC118QSB7 | K21: HP | L21: LE1711 | M21: LATORRE 2442 | N21: 1 | O21: ANTOFAGASTA | P21: ANTOFAGASTA | Q21: ANTOFAGASTA | R21: ATENCION CLIENTES | T21: DAYANA RAQUEL FUENTES CASTILLO | U21: EXTERNO
A22: 210000052334-0000 | B22: CGE000382 | C22: =VLOOKUP(B22,CONSOLIDADO!$B$1:$B$722,2,FALSE) -> #N/A | D22: DESKTOP | E22: 1 | F22: SI | G22: MARIA DINORA HUERTA DIAZ | J22: DT4CE7392J0P | K22: HP | L22: 280 G2 | M22: LATORRE 2442 | N22: 1 | O22: ANTOFAGASTA | P22: ANTOFAGASTA | Q22: ANTOFAGASTA | R22: ATENCION CLIENTES | T22: MARIA DINORA HUERTA DIAZ | U22: EXTERNO
A23: 210000061184-0000 | B23: CGE000383 | C23: =VLOOKUP(B23,CONSOLIDADO!$B$1:$B$722,2,FALSE) -> #N/A | D23: NOTEBOOK | E23: 1 | F23: NO | G23: YANALET XIMENA MORALES HIDALGO | H23: EJECUTIVOAT_YMH | I23: 5CD207HF5K | J23: NB5CD207HF5K-1 | K23: HP | L23: PROBOOK 440 G8 | M23: LATORRE 2442 | N23: 1 | O23: ANTOFAGASTA | P23: ANTOFAGASTA | Q23: ANTOFAGASTA | R23: ATENCION CLIENTES | S23: SI | T23: YANALET XIMENA MORALES HIDALGO | U23: EXTERNO
A24: 210000016466-0000 | B24: CGE000385 | C24: =VLOOKUP(B24,CONSOLIDADO!$B$1:$B$722,2,FALSE) -> #N/A | D24: MONITOR | E24: 1 | G24: JOHANA DEL CARMEN PIZARRO ACUÑA | I24: CNDX706H728729BL2JNL | K24: DELL | L24: E1709WF | M24: LATORRE 2442 | N24: 1 | O24: ANTOFAGASTA | P24: ANTOFAGASTA | Q24: ANTOFAGASTA | R24: ATENCION CLIENTES | T24: JOHANA DEL CARMEN PIZARRO ACUÑA | U24: EXTERNO
A25: 210000035124 | B25: CGE000387 | C25: =VLOOKUP(B25,CONSOLIDADO!$B$1:$B$722,2,FALSE) -> #N/A | D25: DESKTOP | E25: 1 | F25: SI | G25: MONICA PATRICIA KALASIC OLAVE | I25: MXL136182F | J25: NO VISIBLE | K25: HP | L25: COMPAQ 8200 | M25: PEDRO AGUIRRE CERDA 5558 | N25: 1 | O25: ANTOFAGASTA | P25: ANTOFAGASTA | Q25: ANTOFAGASTA | R25: SECRETARIA | T25: N/A | U25: INTERNO | W25: EQUIPO SIN USO NO TIENE MONITOR PISO 1
A26: 2100000016212-0000 | B26: CGE000390 | C26: =VLOOKUP(B26,CONSOLIDADO!$B$1:$B$722,2,FALSE) -> #N/A | D26: MONITOR | E26: 1 | F26: SI | G26: JUAN IGANCIO PINTO BARRAZA | I26: CN0N300H641809CB196L | J26: N/A | K26: DELL | L26: E1709WC | M26: PEDRO AGUIRRE CERDA 5558 | N26: 1 | O26: ANTOFAGASTA | P26: ANTOFAGASTA | Q26: ANTOFAGASTA | R26: DELEGACIÓN | T26: JUAN IGANCIO PINTO BARRAZA | U26: INTERNO | W26: PISO 1
A27: 210000015057-0000 | B27: CGE000392 | C27: =VLOOKUP(B27,CONSOLIDADO!$B$1:$B$722,2,FALSE) -> #N/A | D27: DESKTOP | E27: 1 | F27: SI | G27: RODRIGO LORCA PEREZ | I27: J9K2FA01 | K27: DELL | L27: OPTIPLEX 380 | M27: PEDRO AGUIRRE CERDA 5558 | N27: 1 | O27: ANTOFAGASTA | P27: ANTOFAGASTA | Q27: ANTOFAGASTA | R27: DELEGACIÓN | T27: RODRIGO LORCA PEREZ | U27: INTERNO | W27: PC SIN USO Y SIN MONITOR PISO 1
A28: 210000063000-0000 | B28: CGE000394 | C28: =VLOOKUP(B28,CONSOLIDADO!$B$1:$B$722,2,FALSE) -> #N/A | D28: NOTEBOOK | E28: 1 | F28: SI | G28: RODRIGO LORCA PEREZ | I28: HSNQ32C4 | J28: NB5CD30855HF-1 | K28: HP | L28: HQ TRE 71025 | M28: PEDRO AGUIRRE CERDA 5558 | N28: 1 | O28: ANTOFAGASTA | P28: ANTOFAGASTA | Q28: ANTOFAGASTA | R28: DELEGACIÓN | T28: RODRIGO LORCA PEREZ | U28: INTERNO | W28: PISO 1
A29: 210000016259-0000 | B29: CGE000395 | C29: =VLOOKUP(B29,CONSOLIDADO!$B$1:$B$722,2,FALSE) -> #N/A | D29: MONITOR | E29: 1 | F29: SI | G29: JAVIER IGNACIO SANTIAGO ESPOZ | H29: N/A | I29: CN0N300H641809C81B9L | K29: DELL | L29: E1709WC | M29: PEDRO AGUIRRE CERDA 5558 | N29: 1 | O29: ANTOFAGASTA | P29: ANTOFAGASTA | Q29: ANTOFAGASTA | R29: DELEGACIÓN | T29: JAVIER IGNACIO SANTIAGO ESPOZ | U29: INTERNO | W29: SE ENCUENTRA EN TERRENO PISO 1
A30: 210000038636-0000 | B30: CGE000396 | C30: =VLOOKUP(B30,CONSOLIDADO!$B$1:$B$722,2,FALSE) -> #N/A | D30: DOCKING | E30: 1 | F30: SI | G30: RODRIGO LORCA PEREZ | H30: RHLORCAP | I30: 5CG522ZTLC | J30: N/A | K30: HP | L30: 2013 | M30: PEDRO AGUIRRE CERDA 5558 | N30: 1 | O30: ANTOFAGASTA | P30: ANTOFAGASTA | Q30: ANTOFAGASTA | R30: DELEGACIÓN | T30: RODRIGO LORCA PEREZ | U30: INTERNO | W30: PISO 1
A31: 210000045159-0000 | B31: CGE000397 | C31: =VLOOKUP(B31,CONSOLIDADO!$B$1:$B$722,2,FALSE) -> #N/A | D31: NOTEBOOK | E31: 1 | F31: SI | G31: RODRIGO LORCA PEREZ | I31: 5CG6314737 | J31: NO VISIBLE | K31: HP | L31: 840 G3 | M31: PEDRO AGUIRRE CERDA 5558 | N31: 1 | O31: ANTOFAGASTA | P31: ANTOFAGASTA | Q31: ANTOFAGASTA | R31: DELEGACIÓN | T31: RODRIGO LORCA PEREZ | U31: INTERNO | W31: PISO 1
A32: 210000028593-0000 | B32: CGE000398 | C32: =VLOOKUP(B32,CONSOLIDADO!$B$1:$B$722,2,FALSE) -> #N/A | D32: MONITOR | E32: 1 | F32: SI | G32: DANIEL PEREZ MARRE | H32: N/A | I32: CNC117Q05X | J32: N/A | K32: HP | L32: LE1711 | M32: PEDRO AGUIRRE CERDA 5558 | N32: 1 | O32: ANTOFAGASTA | P32: ANTOFAGASTA | Q32: ANTOFAGASTA | R32: PROYECTOS ESPECIALES | T32: DANIEL PEREZ MARRE | U32: INTERNO | W32: PISO 1
A33: 210000050370-0000 | B33: CGE000399 | C33: =VLOOKUP(B33,CONSOLIDADO!$B$1:$B$722,2,FALSE) -> #N/A | D33: DOCKING | E33: 1 | F33: SI | G33: DANIEL PEREZ MARRE | H33: N/A | I33: 5CC747XJXP | J33: N/A | K33: HP | L33: HP 2013 | M33: PEDRO AGUIRRE CERDA 5558 | N33: 1 | O33: ANTOFAGASTA | P33: ANTOFAGASTA | Q33: ANTOFAGASTA | R33: PROYECTOS ESPECIALES | T33: DANIEL PEREZ MARRE | U33: INTERNO | W33: PISO 1
A34: 210000045739-0000 | B34: CGE000400 | C34: =VLOOKUP(B34,CONSOLIDADO!$B$1:$B$722,2,FALSE) -> #N/A | D34: NOTEBOOK | E34: 1 | F34: SI | G34: DANIEL PEREZ MARRE | H34: DAPEREZM | I34: 5CG6411YYX | K34: HP | L34: 840 G3 | M34: PEDRO AGUIRRE CERDA 5558 | N34: 1 | O34: ANTOFAGASTA | P34: ANTOFAGASTA | Q34: ANTOFAGASTA | R34: PROYECTOS ESPECIALES | S34: SI | T34: DANIEL PEREZ MARRE | U34: INTERNO | W34: PISO 1
A35: 2100000026737-0000 | B35: CGE000406 | C35: =VLOOKUP(B35,CONSOLIDADO!$B$1:$B$722,2,FALSE) -> #N/A | D35: MONITOR | E35: 1 | F35: SI | G35: SOPORTENI | I35: CNC118QQD5 | K35: HP | L35: LE1711 | M35: PEDRO AGUIRRE CERDA 5558 | N35: 2 | O35: ANTOFAGASTA | P35: ANTOFAGASTA | Q35: ANTOFAGASTA | R35: CIERRE DE PROYECTO | T35: SOPORTENI
A36: 210000026340-0000 | B36: CGE000409 | C36: =VLOOKUP(B36,CONSOLIDADO!$B$1:$B$722,2,FALSE) -> #N/A | D36: DESKTOP | E36: 1 | F36: SI | G36: CARLOS GOMEZ GOMEZ | H36: ESTAFETANT | I36: MXL1341P8G | K36: HP | L36: COMPAQ 8200 | M36: PEDRO AGUIRRE CERDA 5558 | N36: 1 | O36: ANTOFAGASTA | P36: ANTOFAGASTA | Q36: ANTOFAGASTA | R36: UNIDAD DE SERVICIOS | T36: CARLOS GOMEZ GOMEZ | U36: INTERNO | W36: PISO 1
A37: 210000029866-0000 | B37: CGE000410 | C37: =VLOOKUP(B37,CONSOLIDADO!$B$1:$B$722,2,FALSE) -> #N/A | D37: MONITOR | E37: 1 | F37: SI | G37: JUAN MAXIMO CHIDA OVIEDO | I37: 3CQ132B98P | K37: HP | L37: LE1711 | M37: PEDRO AGUIRRE CERDA 5558 | N37: 2 | O37: ANTOFAGASTA | P37: ANTOFAGASTA | Q37: ANTOFAGASTA | R37: CGE TRANSMISIÓN | T37: JUAN MAXIMO CHIDA OVIEDO | U37: INTERNO
A38: 210000036584-0000 | B38: CGE000411 | C38: =VLOOKUP(B38,CONSOLIDADO!$B$1:$B$722,2,FALSE) -> #N/A | D38: DESKTOP | E38: 1 | F38: SI | G38: SANDRA JAQUELINE MIRANDA GUERRA | H38: SJMIRANDAG | I38: MXL3613NT | K38: HP | L38: COMPAQ 8200 ELITE SMALL | M38: PEDRO AGUIRRE CERDA 5558 | N38: 2 | O38: ANTOFAGASTA | P38: ANTOFAGASTA | Q38: ANTOFAGASTA | R38: SECRETARIA | T38: SANDRA JAQUELINE MIRANDA GUERRA | U38: INTERNO | W38: EQUIPO SIN USO PUESTO COMO SOPORTE DE NOTEBOOK
A39: 210000016747-0000 | B39: CGE000412 | C39: =VLOOKUP(B39,CONSOLIDADO!$B$1:$B$722,2,FALSE) -> #N/A | D39: MONITOR | E39: 1 | F39: SI | G39: JORGE RODRÍGUEZ MARTINEZ | H39: JERODRIGUEZM | I39: CN0N300641809BF1WEL | J39: N/A | K39: DELL | L39: E1709WG | M39: PEDRO AGUIRRE CERDA 5558 | N39: 1 | O39: ANTOFAGASTA | P39: ANTOFAGASTA | Q39: ANTOFAGASTA | R39: OFICINA DE PERSONAL | T39: JORGE RODRÍGUEZ MARTÍNEZ | U39: INTERNO | W39: PISO 1
A40: 210000029906-0000 | B40: CGE000413 | C40: =VLOOKUP(B40,CONSOLIDADO!$B$1:$B$722,2,FALSE) -> #N/A | D40: MONITOR | E40: 1 | F40: SI | G40: KATHLIN PEREZ FLORES | H40: KMPEREZF | I40: CNC117Q17V | J40: N/A | K40: HP | L40: LE1711 | M40: PEDRO AGUIRRE CERDA 5558 | N40: 1 | O40: ANTOFAGASTA | P40: ANTOFAGASTA | Q40: ANTOFAGASTA | R40: ADMINISTRATIVA | T40: KATHLIN PEREZ FLORES | U40: INTERNO | W40: PISO 1
A41: 210000034723-0000 | B41: CGE000414 | C41: =VLOOKUP(B41,CONSOLIDADO!$B$1:$B$722,2,FALSE) -> #N/A | D41: DESKTOP | E41: 1 | F41: SI | G41: KATHLIN PEREZ FLORES | H41: KMPEREZF | I41: MXL1241D9W | J41: N/A | K41: HP | L41: COMPAQ 8200 | M41: PEDRO AGUIRRE CERDA 5558 | N41: 1 | O41: ANTOFAGASTA | P41: ANTOFAGASTA | Q41: ANTOFAGASTA | R41: ADMINISTRATIVA | T41: KATHLIN PEREZ FLORES | U41: INTERNO | W41: PISO 1
A42: NO TIENE | B42: CGE000415 | C42: =VLOOKUP(B42,CONSOLIDADO!$B$1:$B$722,2,FALSE) -> #N/A | D42: MONITOR | E42: 1 | F42: SI | G42: SOPORTENI | I42: CN0G8TVHQDC0014G0ISBA16 | K42: DELL | L42: P2419H | M42: PEDRO AGUIRRE CERDA 5558 | N42: 2 | O42: ANTOFAGASTA | P42: ANTOFAGASTA | Q42: ANTOFAGASTA | R42: CGE TRANSMISIÓN | T42: SOPORTENI | U42: INTERNO
A43: NO TIENE | B43: CGE000416 | C43: =VLOOKUP(B43,CONSOLIDADO!$B$1:$B$722,2,FALSE) -> #N/A | D43: MONITOR | E43: 1 | F43: SI | G43: SOPORTENI | I43: CN0G8TVHQDC001410HHBA16 | K43: DELL | L43: P2419H | M43: PEDRO AGUIRRE CERDA 5558 | N43: 2 | O43: ANTOFAGASTA | P43: ANTOFAGASTA | Q43: ANTOFAGASTA | R43: CGE TRANSMISIÓN | T43: SOPORTENI | U43: INTERNO
A44: NO TIENE | B44: CGE000417 | C44: =VLOOKUP(B44,CONSOLIDADO!$B$1:$B$722,2,FALSE) -> #N/A | D44: MONITOR | E44: 1 | F44: SI | G44: SOPORTENI | I44: CN0G8TVHQDC001410H6BA16 | K44: DELL | L44: P2419H | M44: PEDRO AGUIRRE CERDA 5558 | N44: 2 | O44: ANTOFAGASTA | P44: ANTOFAGASTA | Q44: ANTOFAGASTA | R44: CGE TRANSMISIÓN | T44: SOPORTENI | U44: INTERNO
A45: 210000016612-0000 | B45: CGE000418 | C45: =VLOOKUP(B45,CONSOLIDADO!$B$1:$B$722,2,FALSE) -> #N/A | D45: MONITOR | E45: 1 | F45: SI | G45: JESSICA VARELA VALENZUELA | I45: CN0U072N641809BA3ZZU | K45: DELL | L45: E170SC | M45: PEDRO AGUIRRE CERDA 5558 | N45: 2 | O45: ANTOFAGASTA | P45: ANTOFAGASTA | Q45: ANTOFAGASTA | R45: COMERCIALIZADORA | T45: JESSICA VARELA VALENZUELA | U45: INTERNO | W45: USUARIA DE LICENCIA
A46: 2100000034978-0000 | B46: CGE000420 | C46: =VLOOKUP(B46,CONSOLIDADO!$B$1:$B$722,2,FALSE) -> #N/A | D46: MONITOR | E46: 1 | F46: SI | G46: MAURICIO QUILONGO ORRAYAN | I46: 3CQ132BB90 | K46: HP | L46: LE1711 | M46: PEDRO AGUIRRE CERDA 5558 | N46: 2 | O46: ANTOFAGASTA | P46: ANTOFAGASTA | Q46: ANTOFAGASTA | R46: PREVENCIONISTA | S46: SI | T46: MAURICIO QUILONGO ORRAYAN | U46: INTERNO | W46: USUARIO DE LICENCIA
A47: NO TIENE | B47: CGE000425 | C47: =VLOOKUP(B47,CONSOLIDADO!$B$1:$B$722,2,FALSE) -> #N/A | D47: MONITOR | E47: 1 | F47: SI | G47: JESSICA VARELA VALENZUELA | I47: CNN7140H5Q | K47: HP | L47: HSTND-2L08 | M47: PEDRO AGUIRRE CERDA 5558 | N47: 2 | O47: ANTOFAGASTA | P47: ANTOFAGASTA | Q47: ANTOFAGASTA | R47: COMERCIALIZADORA | T47: JESSICA VARELA VALENZUELA | U47: INTERNO | W47: USUARIA DE LICENCIA
A48: 210000028196-0000 | B48: CGE000426 | C48: =VLOOKUP(B48,CONSOLIDADO!$B$1:$B$722,2,FALSE) -> #N/A | D48: MONITOR | E48: 1 | F48: SI | G48: REINALDO RAUL MIRANDA DIAS | I48: CNC122NVWT | K48: HP | L48: LE1711 | M48: PEDRO AGUIRRE CERDA 5558 | N48: 2 | O48: ANTOFAGASTA | P48: ANTOFAGASTA | Q48: ANTOFAGASTA | R48: CGE TRANSMISIÓN | T48: REINALDO RAUL MIRANDA DIAS | U48: INTERNO
A49: 2100000060168-0000 | B49: CGE000430 | C49: =VLOOKUP(B49,CONSOLIDADO!$B$1:$B$722,2,FALSE) -> #N/A | D49: NOTEBOOK | E49: 1 | F49: SI | G49: NECTOR RIVERO HENRIQUEZ | H49: NERIVEROH | I49: R9136YX2 | J49: NBR9136YX2 | K49: LENOVO | L49: L13 YOGA | M49: PEDRO AGUIRRE CERDA 5558 | N49: 2 | O49: ANTOFAGASTA | P49: ANTOFAGASTA | Q49: ANTOFAGASTA | R49: DIRECCIÓN DE PROYECTOS | S49: NO | T49: NECTOR RIVERO HENRIQUEZ | U49: INTERNO
A50: 210000017940-0000 | B50: CGE000433 | C50: =VLOOKUP(B50,CONSOLIDADO!$B$1:$B$722,2,FALSE) -> #N/A | D50: MONITOR | E50: 1 | F50: SI | G50: FRANCISCO BRAVO BAEZA | H50: FJBRAVOB | I50: CN0N300H641809BF1VNL | J50: N/A | K50: DELL | L50: E170WC | M50: PEDRO AGUIRRE CERDA 5558 | N50: 1 | O50: ANTOFAGASTA | P50: ANTOFAGASTA | Q50: ANTOFAGASTA | R50: DELEGACIÓN ANTOFAGASTA | T50: FRANCISCO BRAVO BAEZA | U50: INTERNO | W50: PISO 1
A51: 210000016887-0000 | B51: CGE000435 | C51: =VLOOKUP(B51,CONSOLIDADO!$B$1:$B$722,2,FALSE) -> #N/A | D51: MONITOR | E51: 1 | F51: SI | G51: CARMEN GLORIA SANTIBAÑEZ SALAS | H51: N/A | I51: CN0N445N7426101N2GVU | J51: N/A | K51: DELL | L51: E170SB | M51: PEDRO AGUIRRE CERDA 5558 | N51: 1 | O51: ANTOFAGASTA | P51: ANTOFAGASTA | Q51: ANTOFAGASTA | R51: COMERCIAL | T51: CARMEN GLORIA SANTIBAÑEZ SALAS | U51: INTERNO | W51: PISO 1
A52: 210000016255-0000 | B52: CGE000436 | C52: =VLOOKUP(B52,CONSOLIDADO!$B$1:$B$722,2,FALSE) -> #N/A | D52: MONITOR | E52: 1 | F52: SI | G52: CECILIA HINOJOSA VILLA | I52: CN0N300H641809C81BKL | K52: DELL | L52: E1709C | M52: PEDRO AGUIRRE CERDA 5558 | N52: 1 | O52: ANTOFAGASTA | P52: ANTOFAGASTA | Q52: ANTOFAGASTA | R52: CORDINACION DE PROVEEDORES | S52: NO | T52: CECILIA HINOJOSA VILLA | U52: INTERNO | W52: USUARIA SE ENCUENTRA DE LICENCIA PISO 2
A53: 210000029903-0000 | B53: CGE000439 | C53: =VLOOKUP(B53,CONSOLIDADO!$B$1:$B$722,2,FALSE) -> #N/A | D53: MONITOR | E53: 1 | F53: SI | G53: CRISTIAN SAN MARTIN VILLAROEL | I53: CNC111R595 | K53: HP | L53: LE1711 | M53: PEDRO AGUIRRE CERDA 5558 | N53: 2 | O53: ANTOFAGASTA | P53: ANTOFAGASTA | Q53: ANTOFAGASTA | R53: PROGRAMACIÓN | T53: CRISTIAN SAN MARTIN VILLAROEL | U53: INTERNO
A54: 2100000059987-0000 | B54: CGE000440 | C54: =VLOOKUP(B54,CONSOLIDADO!$B$1:$B$722,2,FALSE) -> #N/A | D54: DESKTOP | E54: 1 | F54: SI | G54: CRISTIAN SAN MARTIN VILLAROEL | H54: APOYOCSMV | I54: MJ0EJYZM | J54: DTMJ0EJYZM | K54: LENOVO | L54: M70S | M54: PEDRO AGUIRRE CERDA 5558 | N54: 2 | O54: ANTOFAGASTA | P54: ANTOFAGASTA | Q54: ANTOFAGASTA | R54: PROGRAMACIÓN | T54: CRISTIAN SAN MARTIN VILLAROEL | U54: INTERNO
A55: NO TIENE | B55: CGE000441 | C55: =VLOOKUP(B55,CONSOLIDADO!$B$1:$B$722,2,FALSE) -> #N/A | D55: MONITOR | E55: 1 | F55: SI | G55: SOPORTENI | H55: CAORTESA | I55: CN04Y2817161848SABGQ | J55: N/A | K55: DELL | L55: 1901FP | M55: PEDRO AGUIRRE CERDA 5558 | N55: 1 | O55: ANTOFAGASTA | P55: ANTOFAGASTA | Q55: ANTOFAGASTA | R55: DELEGACIÓN | T55: CLAUDIO CORTES AHUMADA | U55: INTERNO | W55: REVISAR POR CARINA GALLARDO, PISO 1
A56: 2100000016129-0000 | B56: CGE000445 | C56: =VLOOKUP(B56,CONSOLIDADO!$B$1:$B$722,2,FALSE) -> #N/A | D56: MONITOR | E56: 1 | F56: SI | G56: OSCAR HERNRIQUEZ SEGOVIA COLLADO | I56: CN0N300H641809C81HDL | K56: DELL | L56: E1709WC | M56: PEDRO AGUIRRE CERDA 5558 | N56: 2 | O56: ANTOFAGASTA | P56: ANTOFAGASTA | Q56: ANTOFAGASTA | R56: CGE TRANSMISIÓN | T56: OSCAR SEGOVIA COLLADO | U56: INTERNO
A57: 7107 | B57: CGE000447 | C57: =VLOOKUP(B57,CONSOLIDADO!$B$1:$B$722,2,FALSE) -> #N/A | D57: MONITOR | E57: 1 | F57: SI | G57: LESLIE GISSELA VILLAGRAN MIRANDA | I57: CN0N300H641809BU04FL | K57: DELL | L57: E1709WC | M57: PEDRO AGUIRRE CERDA 5558 | N57: 1 | O57: ANTOFAGASTA | P57: ANTOFAGASTA | Q57: ANTOFAGASTA | R57: CORDINACION DE PROVEEDORES | S57: NO | T57: LESLIE GISSELA VILLAGRAN MIRANDA | U57: INTERNO | W57: PISO 2
A58: 210000049979-0000 | B58: CGE000448 | C58: =VLOOKUP(B58,CONSOLIDADO!$B$1:$B$722,2,FALSE) -> #N/A | D58: NOTEBOOK | E58: 1 | F58: SI | G58: JORGE RODRÍGUEZ MARTINEZ | H58: JERODRIGUEZM | I58: 5CG7493Y19 | J58: NB5CG7493Y19 | K58: HP | L58: 840 G3 | M58: PEDRO AGUIRRE CERDA 5558 | N58: 1 | O58: ANTOFAGASTA | P58: ANTOFAGASTA | Q58: ANTOFAGASTA | R58: OFICINA DE PERSONAL | S58: NO | T58: JORGE RODRÍGUEZ MARTÍNEZ | U58: INTERNO | W58: PISO 1
A59: 210000035126 | B59: CGE000451 | C59: =VLOOKUP(B59,CONSOLIDADO!$B$1:$B$722,2,FALSE) -> #N/A | D59: DESKTOP | E59: 1 | F59: SI | G59: JORGE RODRÍGUEZ MARTINEZ | H59: JERODRIGUEZM | I59: MXL1341PLL | J59: DTMXL1341PLL-1 | K59: HP | L59: COMPAQ 8200 | M59: PEDRO AGUIRRE CERDA 5558 | N59: 1 | O59: ANTOFAGASTA | P59: ANTOFAGASTA | Q59: ANTOFAGASTA | R59: OFICINA DE PERSONAL | S59: NO | T59: JORGE RODRÍGUEZ MARTÍNEZ | U59: INTERNO | W59: PISO 1
A60: 210000030211-0000 | B60: CGE000455 | C60: =VLOOKUP(B60,CONSOLIDADO!$B$1:$B$722,2,FALSE) -> #N/A | D60: NOTEBOOK | E60: 1 | F60: SI | G60: MONICA PATRICIA KALASIC OLAVE | H60: MPKARLASICO | I60: MPNXB9417CED | J60: NBMP1J71WY | K60: LENOVO | L60: S340-14IWL | M60: PEDRO AGUIRRE CERDA 5558 | N60: 1 | O60: ANTOFAGASTA | P60: ANTOFAGASTA | Q60: ANTOFAGASTA | R60: SECRETARIA | T60: MONICA PATRICIA KALASIC OLAVE | U60: INTERNO | W60: PISO 1
A61: 210000060211-0000 | B61: CGE000467 | C61: =VLOOKUP(B61,CONSOLIDADO!$B$1:$B$722,2,FALSE) -> #N/A | D61: NOTEBOOK | E61: 1 | F61: SI | G61: SERGIO LUIS BUJES PINTO | H61: SLBUJESP | I61: R9136YQ6 | J61: NBR9136YQ6-01 | K61: LENOVO | L61: L13 YOGA | M61: PEDRO AGUIRRE CERDA 5558 | N61: 1 | O61: ANTOFAGASTA | P61: ANTOFAGASTA | Q61: ANTOFAGASTA | R61: COMERCIAL | S61: NO | T61: SERGIO LUIS BUJES PINTO | U61: INTERNO | W61: PISO 1
A62: 210000030207-0000 | B62: CGE000468 | C62: =VLOOKUP(B62,CONSOLIDADO!$B$1:$B$722,2,FALSE) -> #N/A | D62: NOTEBOOK | E62: 1 | F62: SI | G62: LUIS JAVIER COLINA OSSANDON | I62: MP1NZT72 | J62: NBMP1NZT72 | K62: LENOVO | L62: IDEAPAD S340 | M62: PEDRO AGUIRRE CERDA 5558 | N62: 1 | O62: ANTOFAGASTA | P62: ANTOFAGASTA | Q62: ANTOFAGASTA | R62: COMERCIAL | S62: NO | T62: LUIS JAVIER COLINA OSSANDON | U62: INTERNO | W62: PISO 1
A63: NO TIENE | B63: CGE000470 | C63: =VLOOKUP(B63,CONSOLIDADO!$B$1:$B$722,2,FALSE) -> #N/A | D63: MONITOR | E63: 1 | F63: SI | G63: PATRICIO ALEJANDRO VELASQUEZ PARRA | I63: CN0N300H641809C81J1L | K63: DELL | L63: E1709WC | M63: PEDRO AGUIRRE CERDA 5558 | N63: 2 | O63: ANTOFAGASTA | P63: ANTOFAGASTA | Q63: ANTOFAGASTA | R63: CGE TRANSMISIÓN | T63: PATRICIO ALEJANDRO VELASQUEZ PARRA | U63: INTERNO | W63: REVISAR POR CARINA GALLARDO
A64: 6967 | B64: CGE002248 | C64: =VLOOKUP(B64,CONSOLIDADO!$B$1:$B$722,2,FALSE) -> #N/A | D64: MONITOR | E64: 1 | F64: NO | G64: VALERIA AISSY TAPIA RIOS | I64: CN0X706H72B729C11YTL | K64: DELL | L64: E1709WF | M64: LATORRE 2442 | N64: 1 | O64: ANTOFAGASTA | P64: ANTOFAGASTA | Q64: ANTOFAGASTA | R64: ATENCION CLIENTES | T64: VALERIA AISSY TAPIA RIOS | U64: EXTERNO
A65: 210000027811-0000 | B65: CGE002251 | C65: =VLOOKUP(B65,CONSOLIDADO!$B$1:$B$722,2,FALSE) -> #N/A | D65: DESKTOP | E65: 1 | F65: NO | G65: VALERIA AISSY TAPIA RIOS | H65: VATAPIAR | I65: MXL1312JN2 | J65: DTMXL1312JN2 | K65: HP | L65: COMPAQ 8200 ELITE SMALL | M65: LATORRE 2442 | N65: 1 | O65: ANTOFAGASTA | P65: ANTOFAGASTA | Q65: ANTOFAGASTA | R65: ATENCION CLIENTES | T65: VALERIA AISSY TAPIA RIOS | U65: EXTERNO
A66: 210000061592-0000 | B66: CGE002517 | C66: =VLOOKUP(B66,CONSOLIDADO!$B$1:$B$722,2,FALSE) -> #N/A | D66: NOTEBOOK | E66: 1 | F66: SI | G66: CELSO GABRIEL SAAVEDRA PALMA | I66: 5CD207HCG3 | J66: NB5CD207HCG3 | K66: HP | L66: PROBOOK 440 G8 | M66: PEDRO AGUIRRE CERDA 5558 | N66: 1 | O66: ANTOFAGASTA | P66: ANTOFAGASTA | Q66: ANTOFAGASTA | R66: CGE TRANSMISIÓN | T66: CELSO GABRIEL SAAVEDRA PALMA | U66: INTERNO
A67: 210000030266-0000 | B67: CGE002906 | C67: =VLOOKUP(B67,CONSOLIDADO!$B$1:$B$722,2,FALSE) -> #N/A | D67: NOTEBOOK | E67: 1 | F67: SI | G67: ARMANDO OLIVARES GONZÁLEZ | H67: AAOLIVAREZG | I67: PF1W5YD6 | J67: NBPF1W5YD6-2 | K67: LENOVO | M67: PEDRO AGUIRRE CERDA 5558 | N67: 1 | O67: ANTOFAGASTA | P67: ANTOFAGASTA | Q67: ANTOFAGASTA | R67: COMERCIAL | S67: SI | T67: ARMANDO OLIVARES GONZÁLEZ | U67: INTERNO | W67: PISO 1
A68: 210000024645-0000 | B68: CGE003139 | C68: =VLOOKUP(B68,CONSOLIDADO!$B$1:$B$722,2,FALSE) -> #N/A | D68: MONITOR | E68: 1 | F68: SI | G68: OSCAR MAURICIO VIDELA INOSTROZA | I68: CNC114QD9K | L68: LE1711 | M68: PEDRO AGUIRRE CERDA 5558 | N68: 2 | O68: ANTOFAGASTA | P68: ANTOFAGASTA | Q68: ANTOFAGASTA | R68: DESPACHO DE OPERACIÓN | T68: OSCAR MAURICIO VIDELA INOSTROZA | U68: INTERNO
A69: 210000043730-0000 | B69: CGE003610 | C69: =VLOOKUP(B69,CONSOLIDADO!$B$1:$B$722,2,FALSE) -> #N/A | D69: NOTEBOOK | E69: 1 | F69: SI | G69: JOSEFA CAROLINA NUÑES SAN MARTIN | H69: JNUNEZSM | I69: 5CG61343H0 | J69: 5NB5CG61343H0 | K69: HP | L69: 820 G3 | M69: PEDRO AGUIRRE CERDA 5558 | N69: 1 | O69: ANTOFAGASTA | P69: ANTOFAGASTA | Q69: ANTOFAGASTA | R69: CORDINACION DE PROVEEDORES | S69: NO | T69: JOSEFA CAROLINA NUÑES SAN MARTIN | U69: INTERNO | W69: PISO 2
A70: 2100000641158-0000 | B70: CGE005012 | C70: =VLOOKUP(B70,CONSOLIDADO!$B$1:$B$722,2,FALSE) -> #N/A | D70: NOTEBOOK | E70: 1 | F70: SI | G70: FRANCISCO BRAVO BAEZA | H70: FJBRAVOB | I70: FMRBL24 | J70: NBFMRBL24 | K70: DELL | L70: LATITUDE 5440 | M70: PEDRO AGUIRRE CERDA 5558 | N70: 1 | O70: ANTOFAGASTA | P70: ANTOFAGASTA | Q70: ANTOFAGASTA | R70: DELEGACIÓN ANTOFAGASTA | S70: NO | T70: FRANCISCO BRAVO BAEZA | U70: INTERNO | W70: PISO 1
A71: 210000064159-0000 | B71: CGE005013 | C71: =VLOOKUP(B71,CONSOLIDADO!$B$1:$B$722,2,FALSE) -> #N/A | D71: NOTEBOOK | E71: 1 | F71: SI | G71: FRANCISCO BRAVO BAEZA | H71: FJBRAVOB | I71: D9XRK24 | J71: NBD9XRK24 | K71: DELL | L71: P165G | M71: PEDRO AGUIRRE CERDA 5558 | N71: 1 | O71: ANTOFAGASTA | P71: ANTOFAGASTA | Q71: ANTOFAGASTA | R71: DELEGACIÓN ANTOFAGASTA | T71: FRANCISCO BRAVO BAEZA | U71: INTERNO | W71: PISO 1
A72: 210000030058-0000 | B72: CGE005053 | C72: =VLOOKUP(B72,CONSOLIDADO!$B$1:$B$722,2,FALSE) -> #N/A | D72: NOTEBOOK | E72: 1 | F72: NO | G72: DAYANA RAQUEL FUENTES CASTILLO | H72: DRFUENTESC | I72: PC18MZLP | J72: NBPC18MZLP | K72: LENOVO | L72: X390 G8 | M72: LATORRE 2442 | N72: 1 | O72: ANTOFAGASTA | P72: ANTOFAGASTA | Q72: ANTOFAGASTA | R72: ATENCION CLIENTES | S72: SI | T72: DAYANA RAQUEL FUENTES CASTILLO | U72: EXTERNO
A73: 2100000063991-0000 | B73: CGE005140 | C73: =VLOOKUP(B73,CONSOLIDADO!$B$1:$B$722,2,FALSE) -> #N/A | D73: MONITOR | E73: 1 | F73: SI | G73: RICARDO SEBASTIAN NEIRA CORDERO | I73: CN0101CFTV2003AH1GWUA01 | K73: DELL | L73: P2422H | M73: PEDRO AGUIRRE CERDA 5558 | N73: 2 | O73: ANTOFAGASTA | P73: ANTOFAGASTA | Q73: ANTOFAGASTA | R73: DESPACHO DE OPERACIÓN | S73: NO | T73: RICARDO SEBASTIAN NEIRA CORDERO | U73: INTERNO
A74: 210000064024-0000 | B74: CGE005143 | C74: =VLOOKUP(B74,CONSOLIDADO!$B$1:$B$722,2,FALSE) -> #N/A | D74: MONITOR | E74: 1 | F74: SI | G74: YENNY LORETO DIAZ ORELLANA | I74: CN0101CFTV2003ABB14BA01 | K74: DELL | L74: P2422H | M74: PEDRO AGUIRRE CERDA 5558 | N74: 1 | O74: ANTOFAGASTA | P74: ANTOFAGASTA | Q74: ANTOFAGASTA | R74: SERVICIOS GENERALES | T74: YENNY LORETO DIAZ ORELLANA | U74: INTERNO
A75: 210000063990-0000 | B75: CGE005175 | C75: =VLOOKUP(B75,CONSOLIDADO!$B$1:$B$722,2,FALSE) -> #N/A | D75: MONITOR | E75: 1 | F75: SI | G75: RICARDO SEBASTIAN NEIRA CORDERO | I75: CN0101CFTV2003AH263UA01 | K75: DELL | L75: P2422H | M75: PEDRO AGUIRRE CERDA 5558 | N75: 2 | O75: ANTOFAGASTA | P75: ANTOFAGASTA | Q75: ANTOFAGASTA | R75: DESPACHO DE OPERACIÓN | T75: RICARDO SEBASTIAN NEIRA CORDERO | U75: INTERNO
A76: 2100000063591-0000 | B76: CGE005216 | C76: =VLOOKUP(B76,CONSOLIDADO!$B$1:$B$722,2,FALSE) -> #N/A | D76: NOTEBOOK | E76: 1 | F76: SI | G76: SANDRA JAQUELINE MIRANDA GUERRA | I76: GPZ79W3 | J76: NBGPZ79W3 | K76: DELL | L76: 5440 G13 | M76: PEDRO AGUIRRE CERDA 5558 | N76: 2 | O76: ANTOFAGASTA | P76: ANTOFAGASTA | Q76: ANTOFAGASTA | R76: SECRETARIA | S76: SI | T76: SANDRA JAQUELINE MIRANDA GUERRA | U76: INTERNO
A77: 210000063765-0000 | B77: CGE005228 | C77: =VLOOKUP(B77,CONSOLIDADO!$B$1:$B$722,2,FALSE) -> #N/A | D77: NOTEBOOK | E77: 1 | F77: SI | G77: JAVIER IGNACIO SANTIAGO ESPOZ | H77: JSANTIGOE | I77: MFGYR:2023 | J77: NB9K8B9W3 | K77: DELL | L77: LATITUDE 5440 | M77: PEDRO AGUIRRE CERDA 5558 | N77: 1 | O77: ANTOFAGASTA | P77: ANTOFAGASTA | Q77: ANTOFAGASTA | R77: DELEGACIÓN | T77: JAVIER IGNACIO SANTIAGO ESPOZ | U77: INTERNO | W77: SE ENCUENTRA EN TERRENO PISO 1
A78: 210000063947-0000 | B78: CGE005322 | C78: =VLOOKUP(B78,CONSOLIDADO!$B$1:$B$722,2,FALSE) -> #N/A | D78: MONITOR | E78: 1 | F78: SI | G78: EDUARDO JOSE GUTIERREZ MARTINEZ | I78: CN0101CF | K78: DELL | L78: P2422H | M78: PEDRO AGUIRRE CERDA 5558 | N78: 2 | O78: ANTOFAGASTA | P78: ANTOFAGASTA | Q78: ANTOFAGASTA | R78: DIRECCIÓN DE PROYECTOS | T78: EDUARDO JOSE GUTIERREZ MARTINEZ | U78: INTERNO
A79: 210000063561-0000 | B79: CGE005462 | C79: =VLOOKUP(B79,CONSOLIDADO!$B$1:$B$722,2,FALSE) -> #N/A | D79: NOTEBOOK | E79: 1 | F79: SI | G79: DANIEL ALEXIS HIDALGO GALLARDO | H79: DAHIDALGOG | I79: 3DJ89W3 | J79: NB3DJ89W3 | K79: DELL | L79: 5440 G13 | M79: PEDRO AGUIRRE CERDA 5558 | N79: 2 | O79: ANTOFAGASTA | P79: ANTOFAGASTA | Q79: ANTOFAGASTA | R79: CGE TRANSMISIÓN | S79: SI | T79: DANIEL ALEXIS HIDALGO GALLARDO | U79: INTERNO
A80: NO TIENE | B80: CGE005553 | C80: =VLOOKUP(B80,CONSOLIDADO!$B$1:$B$722,2,FALSE) -> #N/A | D80: NOTEBOOK | E80: 1 | F80: SI | G80: YENNY LORETO DIAZ ORELLANA | H80: YLDIAZO | I80: 3BHB9W3 | J80: NB3BHB9W3 | K80: DELL | L80: LATITUDE 5440 13G | M80: PEDRO AGUIRRE CERDA 5558 | N80: 1 | O80: ANTOFAGASTA | P80: ANTOFAGASTA | Q80: ANTOFAGASTA | R80: SERVICIOS GENERALES | S80: NO | T80: YENNY LORETO DIAZ ORELLANA | U80: INTERNO
A81: 2100000063657-0000 | B81: CGE005557 | C81: =VLOOKUP(B81,CONSOLIDADO!$B$1:$B$722,2,FALSE) -> #N/A | D81: NOTEBOOK | E81: 1 | F81: SI | G81: JUAN IGANCIO PINTO BARRAZA | H81: JIPINTOB | I81: FN889W3 | J81: NBFN8B9W3 | K81: DELL | L81: LATITUDE 5440 | M81: PEDRO AGUIRRE CERDA 5558 | N81: 1 | O81: ANTOFAGASTA | P81: ANTOFAGASTA | Q81: ANTOFAGASTA | R81: DELEGACIÓN | T81: JUAN IGANCIO PINTO BARRAZA | U81: INTERNO | W81: PISO 1
A82: 210000063792-0000 | B82: CGE005613 | C82: =VLOOKUP(B82,CONSOLIDADO!$B$1:$B$722,2,FALSE) -> #N/A | D82: MONITOR | E82: 1 | F82: SI | G82: EDUARDO JOSE GUTIERREZ MARTINEZ | I82: CN0101CF | K82: DELL | L82: P2422H | M82: PEDRO AGUIRRE CERDA 5558 | N82: 2 | O82: ANTOFAGASTA | P82: ANTOFAGASTA | Q82: ANTOFAGASTA | R82: DIRECCIÓN DE PROYECTOS | T82: EDUARDO JOSE GUTIERREZ MARTINEZ | U82: INTERNO
A83: 2100000063689-0000 | B83: CGE005631 | C83: =VLOOKUP(B83,CONSOLIDADO!$B$1:$B$722,2,FALSE) -> #N/A | D83: NOTEBOOK | E83: 1 | F83: SI | G83: RICARDO SEBASTIAN NEIRA CORDERO | H83: RSNEIRAC | I83: 2R8B9W3 | J83: NB2R8B9W3 | K83: DELL | L83: LATITUDE 5440 G13 | M83: PEDRO AGUIRRE CERDA 5558 | N83: 2 | O83: ANTOFAGASTA | P83: ANTOFAGASTA | Q83: ANTOFAGASTA | R83: DESPACHO DE OPERACIÓN | T83: RICARDO SEBASTIAN NEIRA CORDERO | U83: INTERNO
A84: 210000064175-0000 | B84: CGE006463 | C84: =VLOOKUP(B84,CONSOLIDADO!$B$1:$B$722,2,FALSE) -> #N/A | D84: NOTEBOOK | E84: 1 | F84: SI | G84: MILKO HENRY SANCHEZ SALFATE | H84: MHSANCHEZS | I84: HZ6RK24 | J84: NBHZ6RK24 | K84: DELL | L84: LATITUDE 5440 G13 | M84: PEDRO AGUIRRE CERDA 5558 | N84: 2 | O84: ANTOFAGASTA | P84: ANTOFAGASTA | Q84: ANTOFAGASTA | R84: DESPACHO DE OPERACIÓN | S84: NO | T84: MILKO HENRY SANCHEZ SALFATE | U84: INTERNO
A85: NO TIENE | B85: CGE007226 | C85: =VLOOKUP(B85,CONSOLIDADO!$B$1:$B$722,2,FALSE) -> #N/A | D85: DESKTOP | E85: 1 | F85: SI | G85: JORGE PABLO ESPINOZA BUSTAMANTE | I85: MXL1241QXJ | K85: HP | L85: COMPAQ 8200 | M85: PEDRO AGUIRRE CERDA 5558 | N85: 2 | O85: ANTOFAGASTA | P85: ANTOFAGASTA | Q85: ANTOFAGASTA | R85: DESPACHO DE OPERACIÓN | S85: NO | T85: JORGE PABLO ESPINOZA BUSTAMANTE | U85: INTERNO | W85: REVISAR POR CARINA GALLARDO
A86: 210000016476-0000 | B86: CGE007957 | C86: =VLOOKUP(B86,CONSOLIDADO!$B$1:$B$722,2,FALSE) -> #N/A | D86: MONITOR | E86: 1 | G86: MARIA DINORA HUERTA DIAZ | H86: MDHUERTAD | I86: CN0N300H641809C81JEL | K86: DELL | L86: E1709WF | M86: LATORRE 2442 | N86: 1 | O86: ANTOFAGASTA | P86: ANTOFAGASTA | Q86: ANTOFAGASTA | R86: ATENCION CLIENTES | T86: MARIA DINORA HUERTA DIAZ | U86: EXTERNO
A87: 2100000028379-0000 | B87: CGE007958 | C87: =VLOOKUP(B87,CONSOLIDADO!$B$1:$B$722,2,FALSE) -> #N/A | D87: MONITOR | E87: 1 | F87: SI | G87: NECTOR RIVERO HENRIQUEZ | I87: CNC111R54T | K87: HP | L87: LE1711 | M87: PEDRO AGUIRRE CERDA 5558 | N87: 2 | O87: ANTOFAGASTA | P87: ANTOFAGASTA | Q87: ANTOFAGASTA | R87: DIRECCIÓN DE PROYECTOS | T87: NECTOR RIVERO HENRIQUEZ | U87: INTERNO
A88: 210000066600-0000 | B88: CGE008355 | C88: =VLOOKUP(B88,CONSOLIDADO!$B$1:$B$722,2,FALSE) -> #REF! | D88: MONITOR | E88: 1 | F88: SI | G88: MARIO VERA ALBORNOZ | H88: MAVERAA | I88: W1D2451G0940 | J88: N/A | K88: VIEWSONIC | L88: VG2456 | M88: PEDRO AGUIRRE CERDA 5558 | N88: 1 | O88: ANTOFAGASTA | P88: ANTOFAGASTA | Q88: ANTOFAGASTA | R88: SUBGERENCIA | S88: NO | T88: MARIO VERA ALBORNOZ | U88: INTERNO | W88: PISO 1
A89: 210000065131-0000 | B89: CGE008385 | C89: =VLOOKUP(B89,CONSOLIDADO!$B$1:$B$722,2,FALSE) -> #N/A | D89: NOTEBOOK | E89: 1 | F89: SI | G89: NELSON ANTONIO GALLEGUILLOS TRIBIÑO | H89: NAGALLEGUILLOST | I89: 5CD421CCXW | J89: NB5CD421CCXW | K89: HP | L89: 440 G10 | M89: PEDRO AGUIRRE CERDA 5558 | N89: 1 | O89: ANTOFAGASTA | P89: ANTOFAGASTA | Q89: ANTOFAGASTA | R89: ADMINISTRATIVA | S89: SI | T89: NELSON ANTONIO GALLEGUILLOS TRIBIÑO | U89: INTERNO | W89: PISO 1
A90: 210000024642-0000 | B90: CGE008432 | C90: =VLOOKUP(B90,CONSOLIDADO!$B$1:$B$722,2,FALSE) -> #REF! | D90: MONITOR | E90: 1 | F90: SI | G90: MARIO VERA ALBORNOZ | H90: MAVERAA | I90: CNC114QDQG | J90: N/A | K90: HP | L90: LE1711 | M90: PEDRO AGUIRRE CERDA 5558 | N90: 1 | O90: ANTOFAGASTA | P90: ANTOFAGASTA | Q90: ANTOFAGASTA | R90: SUBGERENCIA | T90: MARIO VERA ALBORNOZ | U90: INTERNO | W90: PISO 1
A91: NO TIENE | B91: CGE008787 | C91: =VLOOKUP(B91,CONSOLIDADO!$B$1:$B$722,2,FALSE) -> #N/A | D91: NOTEBOOK | E91: 1 | F91: SI | G91: CARMEN GLORIA SANTIBAÑEZ SALAS | H91: CGSANTIBANEZ | I91: 81N7000HCL | J91: NBMP1J702-02 | K91: LENOVO | L91: S340 | M91: PEDRO AGUIRRE CERDA 5558 | N91: 1 | O91: ANTOFAGASTA | P91: ANTOFAGASTA | Q91: ANTOFAGASTA | R91: COMERCIAL | S91: NO | T91: CARMEN GLORIA SANTIBAÑEZ SALAS | U91: INTERNO | W91: REVISAR POR CARINA GALLARDO, PISO 1
A92: 210000019357-0000 | B92: CGE008788 | C92: =VLOOKUP(B92,CONSOLIDADO!$B$1:$B$722,2,FALSE) -> #N/A | D92: MONITOR | E92: 1 | F92: SI | G92: LUIS JAVIER COLINA OSSANDON | H92: LJCOLINAO | I92: CN0300H641800251F4L | K92: DELL | L92: E1709WC | M92: PEDRO AGUIRRE CERDA 5558 | N92: 1 | O92: ANTOFAGASTA | P92: ANTOFAGASTA | Q92: ANTOFAGASTA | R92: COMERCIAL | T92: LUIS JAVIER COLINA OSSANDON | U92: INTERNO | W92: PISO 1
A93: NO TIENE | B93: CGE008791 | C93: =VLOOKUP(B93,CONSOLIDADO!$B$1:$B$722,2,FALSE) -> #N/A | D93: NOTEBOOK | E93: 1 | F93: SI | G93: CLAUDIO CORTES AHUMADA | H93: CAORTESA | I93: 5CD207HCL7 | J93: NB5CD207HCL7 | K93: HP | L93: CGE008791 | M93: PEDRO AGUIRRE CERDA 5558 | N93: 1 | O93: ANTOFAGASTA | P93: ANTOFAGASTA | Q93: ANTOFAGASTA | R93: DELEGACIÓN | S93: NO | T93: CLAUDIO CORTES AHUMADA | U93: INTERNO | W93: REVISAR POR CARINA GALLARDO, PISO 1
A94: 210000016218-0000 | B94: CGE008792 | C94: =VLOOKUP(B94,CONSOLIDADO!$B$1:$B$722,2,FALSE) -> #N/A | D94: MONITOR | E94: 1 | F94: SI | G94: JUAN IGANCIO PINTO BARRAZA | I94: CN0N300H641809C818WL | K94: DELL | L94: E1709WC | M94: PEDRO AGUIRRE CERDA 5558 | N94: 1 | O94: ANTOFAGASTA | P94: ANTOFAGASTA | Q94: ANTOFAGASTA | R94: DELEGACIÓN | T94: JUAN IGANCIO PINTO BARRAZA | U94: INTERNO | W94: PISO 1
A95: 2100000028664-0000 | B95: CGE008793 | C95: =VLOOKUP(B95,CONSOLIDADO!$B$1:$B$722,2,FALSE) -> #N/A | D95: MONITOR | E95: 1 | F95: SI | G95: JAVIER IGNACIO SANTIAGO ESPOZ | H95: JSANTIGOE | I95: CNC121RXGB | J95: N/A | K95: HP | L95: LE1711 | M95: PEDRO AGUIRRE CERDA 5558 | N95: 1 | O95: ANTOFAGASTA | P95: ANTOFAGASTA | Q95: ANTOFAGASTA | R95: DELEGACIÓN | T95: JAVIER IGNACIO SANTIAGO ESPOZ | U95: INTERNO | W95: SE ENCUENTRA EN TERRENO PISO 1
A96: 210000024533-0000 | B96: CGE008794 | C96: =VLOOKUP(B96,CONSOLIDADO!$B$1:$B$722,2,FALSE) -> #N/A | D96: MONITOR | E96: 1 | F96: SI | G96: YENNY LORETO DIAZ ORELLANA | I96: CNC109NYNC | K96: HP | L96: LE1711 | M96: PEDRO AGUIRRE CERDA 5558 | N96: 1 | O96: ANTOFAGASTA | P96: ANTOFAGASTA | Q96: ANTOFAGASTA | R96: SERVICIOS GENERALES | T96: YENNY LORETO DIAZ ORELLANA | U96: INTERNO
A97: 210000016264-0000 | B97: CGE008795 | C97: =VLOOKUP(B97,CONSOLIDADO!$B$1:$B$722,2,FALSE) -> #N/A | D97: MONITOR | E97: 1 | F97: SI | G97: CARLOS GOMEZ GOMEZ | I97: CN0N300H641809C81BGL | K97: DELL | L97: E1709WC | M97: PEDRO AGUIRRE CERDA 5558 | N97: 1 | O97: ANTOFAGASTA | P97: ANTOFAGASTA | Q97: ANTOFAGASTA | R97: UNIDAD DE SERVICIOS | T97: CARLOS GOMEZ GOMEZ | U97: INTERNO | W97: PISO 1
A98: 2100000044976-0000 | B98: CGE008802 | C98: =VLOOKUP(B98,CONSOLIDADO!$B$1:$B$722,2,FALSE) -> #N/A | D98: DOCKING | E98: 1 | F98: SI | G98: CECILIA HINOJOSA VILLA | I98: 2.1000004e+15 | J98: 5CG625ZK23 | K98: HP | L98: 2013 | M98: PEDRO AGUIRRE CERDA 5558 | N98: 1 | O98: ANTOFAGASTA | P98: ANTOFAGASTA | Q98: ANTOFAGASTA | R98: CORDINACION DE PROVEEDORES | T98: CECILIA HINOJOSA VILLA | U98: INTERNO | W98: USUARIA SE ENCUENTRA DE LICENCIA, PISO 2
A99: 210000061663-0000 | B99: CGE008803 | C99: =VLOOKUP(B99,CONSOLIDADO!$B$1:$B$722,2,FALSE) -> #N/A | D99: NOTEBOOK | E99: 1 | F99: SI | G99: EDUARDO JOSE GUTIERREZ MARTINEZ | H99: EJGUTIERREZM | I99: 5CD207HDPK | J99: NB5CD207HDPK2 | K99: HP | L99: PROBOOK 440 G8 | M99: PEDRO AGUIRRE CERDA 5558 | N99: 2 | O99: ANTOFAGASTA | P99: ANTOFAGASTA | Q99: ANTOFAGASTA | R99: DIRECCIÓN DE PROYECTOS | S99: NO | T99: EDUARDO JOSE GUTIERREZ MARTINEZ | U99: INTERNO
A100: 7197 | B100: CGE008808 | C100: =VLOOKUP(B100,CONSOLIDADO!$B$1:$B$722,2,FALSE) -> #N/A | D100: NOTEBOOK | E100: 1 | F100: SI | G100: JUAN MAXIMO CHIDA OVIEDO | H100: JMCHIAO | I100: CNU41194MQ | J100: NB-CNU4119MQ | K100: HP | L100: ELITE BOOK 840 G1 | M100: PEDRO AGUIRRE CERDA 5558 | N100: 2 | O100: ANTOFAGASTA | P100: ANTOFAGASTA | Q100: ANTOFAGASTA | R100: CGE TRANSMISIÓN | T100: JUAN MAXIMO CHIDA OVIEDO | U100: INTERNO | W100: EQUIPO EN USO Y DE MUY ANTIGUA GENERACIÓN G1
...

Sheet DUPLICADAS REVISAR
A1: Activo Fijo | B1: Rotulo Entel | C1: Tipo Dispositivo | D1: Unidades | E1: Teléfono | F1: Nombre de Usuario | G1: Usuario de RED | H1: Número de Serie | I1: Hostname | J1: Marca | K1: Modelo | L1: Dirección | M1: Piso | N1: Comuna | O1: Región | P1: Ciudad | Q1: Area | R1: Necesita Alzador | S1: Nombre de usuario Responsable | T1: Tipo Usuario | U1: Observaciones | V1: Observaciones 2
A2: 210000062193-0000 | B2: CGE000033 | C2: MONITOR | D2: 1 | E2: NO | H2: BZRYH4ZT400334E | I2: NO | J2: SAMSUNG | K2: LC24F390FHLXZS | L2: PRESIDENTE RIESCO 5561 | M2: 14 | N2: LAS CONDES | O2: METROPOLITANA | P2: SANTIAGO | Q2: TRANSFORMACION DIGITAL | R2: NO | T2: INTERNO
A3: 210000026729-0000 | B3: CGE000362 | C3: MONITOR | D3: 1 | E3: SI | F3: CELSO GABRIEL SAAVEDRA PALMA | H3: CNC115PR29 | J3: HP | K3: LE1711 | L3: PEDRO AGUIRRE CERDA 5558 | M3: 1 | N3: ANTOFAGASTA | O3: ANTOFAGASTA | P3: ANTOFAGASTA | Q3: GERENCIA | S3: CELSO GABRIEL SAAVEDRA PALMA | T3: INTERNO
A4: 210000061116-0000 | B4: CGE001186 | C4: NOTEBOOK | E4: SI | F4: Magali Cordoba Hinojosa | G4: mmcordovah | H4: 5CD107HD3Z | I4: NB5CD107HD3Z | J4: HP | K4: PROBOOK 440 G8 | L4: Av Presidente riesco 5561 | M4: 12 | N4: Las Condes | O4: Metropolitana | P4: Santiago | Q4: Tesoreria | R4: SI | S4: Karin Valenzuela | T4: INTERNO
A5: 210000029723-0000 | B5: CGE001198 | C5: MONITOR | D5: 1 | E5: SI | F5: PEDRO CORDOVA GALVEZ | G5: PCORDOVAG | H5: 61BCMAR6WWW9057375 | I5: NO | J5: LENOVO | K5: D17238FT0 | L5: PRESIDENTE RIESCO 5561 | M5: 15 | N5: LAS CONDES | O5: METROPOLITANA | P5: SANTIAGO | Q5: PLANIFICACION Y CONSTRUCCION DE LA RED | R5: NO | S5: FERNANDO SANHUEZA | T5: INTERNO
A6: 210000062536-0000 | B6: CGE001237 | C6: NOTEBOOK | D6: 1 | E6: SI | F6: IVAN SEPULVEDA VASQUEZ | G6: ISEPULVEDAV | H6: 5CD236FG8Q | I6: NB5CD236FG8Q | J6: HP | K6: PROBOOK 440 G9 | L6: PRESIDENTE RIESCO 5561 | M6: 15 | N6: LAS CONDES | O6: METROPOLITANA | P6: SANTIAGO | Q6: CONSTRUCCION TX | R6: NO | S6: NELSON ANTILLANCA | T6: INTERNO
A7: 210000062403-0000 | B7: CGE001238 | C7: MONITOR | D7: 1 | E7: SI | F7: IVAN SEPULVEDA VASQUEZ | G7: ISEPULVEDAV | H7: 212NTVS10975 | I7: NO | J7: LG | K7: 24MK430H | L7: PRESIDENTE RIESCO 5561 | M7: 15 | N7: LAS CONDES | O7: METROPOLITANA | P7: SANTIAGO | Q7: CONSTRUCCION TX | R7: NO | S7: NELSON ANTILLANCA | T7: INTERNO
A8: 210000028255-0000 | B8: CGE001342 | C8: MONITOR | D8: 1 | E8: SI | F8: KAREN CORTEZ-MONRROY | G8: KCORTEZM | H8: NO LEGIBLE | I8: NO | J8: HP | K8: LE1711 | L8: PRESIDENTE RIESCO 5561 | M8: PISO 16 | N8: LAS CONDES | O8: METROPOLITANA | P8: SANTIAGO | Q8: PERSONAS | R8: NO | S8: MARIA EUGENIA CID | T8: INTERNO | V8: SERIE NO LEGIBLE
A9: 210000062502-0000 | B9: CGE001346 | C9: NOTEBOOK | D9: 1 | E9: SI | F9: PEDRO VARGAS ABURTO | G9: PJVARGASA | H9: CD236FG92 | I9: NB5CD236FG92 | J9: HP | K9: PROBOOK 440 G9 | L9: PRESIDENTE RIESCO 5561 | M9: 15 | N9: LAS CONDES | O9: METROPOLITANA | P9: SANTIAGO | Q9: PLANIFICACION Y CONSTRUCCION DE LA RED | R9: NO | S9: ADAM CASTILLO SALAS | T9: INTERNO
A10: 210000021080-0000 | B10: CGE001403 | C10: MONITOR | F10: Magali Cordoba Hinojosa | G10: mmcordovah | H10: CN0X706H728721W1L | J10: DELL | K10: E1709WC | L10: Av Presidente riesco 5561 | M10: 12 | N10: Las Condes | O10: Metropolitana | P10: Santiago | Q10: Tesoreria | R10: SI | S10: Karin Valenzuela | T10: INTERNO
A11: 210000062371-0000 | B11: CGE001527 | C11: MONITOR | D11: 1 | E11: SI | F11: GIOVANNY MALLEA VERGARA | G11: GAMALLEAV | H11: 212NTBK10973 | I11: NO | J11: LG | K11: 24MK430H | L11: PDTE. RIESCO 5561 | M11: 16 | N11: LAS CONDES | O11: METROPOLITANA | P11: SANTIAGO | Q11: TARIFAS Y CONTABILIDAD REGULATORIA | R11: NO | S11: NICOLÁS GUTIERREZ ZEPEDA | T11: INTERNO
A12: 210000061612-0001 | B12: CGE001533 | C12: NOTEBOOK | D12: 1 | E12: SI | F12: MILTON HUILIPAN MELIN | G12: MHUILIPANM | H12: CD20M073 | I12: NB5CD20M073 | J12: HP | K12: PROBOOK 440 G7 | L12: PRESIDENTE RIESCO 5561 | M12: 14 | N12: LAS CONDES | O12: METROPOLITANA | P12: SANTIAGO | Q12: COBRANZA | R12: NO | S12: RODRIGO ALQUINTA | T12: INTERNO | V12: USARIO SIN MONITOR
A13: 210000060767-0000 | B13: CGE001570 | C13: NOTEBOOK | D13: 1 | E13: NO | F13: GUILLERMO AYANCA GALLARDO | G13: GAYANCANG | H13: CD1463LMQ | I13: NB5CD1463LMQ | J13: HP | K13: PROBOOK 440 G8 | L13: PRESIDENTE RIESCO 5561 | M13: 15 | N13: LAS CONDES | O13: METROPOLITANA | P13: SANTIAGO | Q13: PLANIFICACION Y CONSTRUCCION DE LA RED | R13: NO | S13: CAMILA BRAVO | T13: INTERNO
A14: 210000026458-0000 | B14: CGE001585 | C14: MONITOR | D14: 1 | E14: NO | F14: SOPORTE NI | G14: NO | H14: CNC115T0J8 | I14: NO | J14: HP | K14: LE1711 | L14: PRESIDENTE RIESCO 5561 | M14: 15 | N14: LAS CONDES | O14: METROPOLITANA | P14: SANTIAGO | Q14: PLANIFICACION Y CONSTRUCCION DE LA RED | R14: NO | S14: SOPORTE NI | T14: INTERNO | V14: MONITOR SOLO EN ESCRITORIO SIN USUARIO
A15: 210000062499-0000 | B15: CGE001598 | C15: NOTEBOOK | D15: 1 | E15: SI | F15: CLAUDIO VALDIVIA STEEL | G15: CAVALDIVIAS | H15: CD236FG95 | I15: NB5CD236FG95 | J15: HP | K15: PROBOOK 440 G9 | L15: PRESIDENTE RIESCO 5561 | M15: 15 | N15: LAS CONDES | O15: METROPOLITANA | P15: SANTIAGO | Q15: PLANIFICACION Y CONSTRUCCION DE LA RED | R15: NO | S15: FELIPE GONZALEZ | T15: INTERNO
A16: NO TIENE | B16: CGE001599 | C16: MONITOR | D16: 1 | E16: SI | F16: CLAUDIO VALDIVIA STEEL | G16: CAVALDIVIAS | H16: M3344554 | I16: NO | J16: ASUS | K16: VG289 | L16: PRESIDENTE RIESCO 5561 | M16: 15 | N16: LAS CONDES | O16: METROPOLITANA | P16: SANTIAGO | Q16: PLANIFICACION Y CONSTRUCCION DE LA RED | R16: NO | S16: FELIPE GONZALEZ | T16: INTERNO | V16: REVISAR POR CARINA GALLARDO
A17: 210000060783-0000 | B17: CGE001666 | C17: NOTEBOOK | D17: 1 | E17: SI | F17: RICHARD CESPEDES MORI | G17: RCESPEDES | H17: CD1463LCW | I17: NB5CD1463LCW | J17: HP | K17: PROBOOK 440 G8 | L17: PRESIDENTE RIESCO 5561 | M17: 15 | N17: LAS CONDES | O17: METROPOLITANA | P17: SANTIAGO | Q17: PLANIFICACION Y CONSTRUCCION DE LA RED | R17: SI | S17: JAVIER SANTORO | T17: INTERNO
A18: 210000021748-0000 | B18: CGE001667 | C18: MONITOR | D18: 1 | E18: SI | F18: RICHARD CESPEDES MORI | G18: RCESPEDES | H18: CN014K0N74445084AZCU | I18: NO | J18: DELL | K18: 014KON | L18: PRESIDENTE RIESCO 5561 | M18: 15 | N18: LAS CONDES | O18: METROPOLITANA | P18: SANTIAGO | Q18: PLANIFICACION Y CONSTRUCCION DE LA RED | R18: SI | S18: JAVIER SANTORO | T18: INTERNO
A19: 210000062492-0000 | B19: CGE001969 | C19: NOTEBOOK | D19: 1 | E19: SI | F19: Susana Marquez Gonzalez | G19: semarquezg | H19: 5CD236FFHT | I19: NB5CD236FFHT | J19: HP | K19: PROBOOK 440 G9 | L19: Av Presidente riesco 5561 | M19: 12 | N19: Las Condes | O19: Metropolitana | P19: Santiago | Q19: Tesoreria | R19: SI | S19: Karin Valenzuela | T19: INTERNO
A20: 210000028284-0000 | B20: CGE001970 | C20: MONITOR | F20: Susana Marquez Gonzalez | G20: semarquezg | H20: CNC112QDPF | J20: HP | K20: LE 1711 | L20: Av Presidente riesco 5561 | M20: 12 | N20: Las Condes | O20: Metropolitana | P20: Santiago | Q20: Tesoreria | R20: SI | S20: Karin Valenzuela | T20: INTERNO
A21: 210000051053-0000 | B21: CGE001984 | C21: NOTEBOOK | E21: NO | F21: Enrique Aravena Cifuentes | G21: earavena | H21: 5CG749632X | I21: NB5CG749632X | J21: HP | K21: ELITEBOOK 840 G3 | L21: Av Presidente riesco 5561 | M21: 12 | N21: Las Condes | O21: Metropolitana | P21: Santiago | Q21: Tesoreria | R21: SI | S21: Karin Valenzuela | T21: INTERNO
A22: 210000060266-0000 | B22: CGE001987 | C22: NOTEBOOK | E22: SI | F22: Yessica Perez Ibarra | G22: yperez | H22: R9136WY0 | I22: NBR9136WY0 | J22: Lenovo | K22: L13 YOGA | L22: Av Presidente riesco 5561 | M22: 12 | N22: Las Condes | O22: Metropolitana | P22: Santiago | Q22: Tesoreria | R22: SI | S22: Karin Valenzuela | T22: INTERNO
A23: 210000026794-0000 | B23: CGE002222 | C23: MONITOR | D23: 1 | E23: NO | F23: SOPORTE NI | G23: NO | H23: CNC115T03H | I23: NO | J23: HP | K23: LE1711 | L23: PRESIDENTE RIESCO 5561 | M23: 15 | N23: LAS CONDES | O23: METROPOLITANA | P23: SANTIAGO | Q23: PLANIFICACION Y CONSTRUCCION DE LA RED | R23: NO | S23: SOPORTE NI | T23: INTERNO | V23: MONITOR SOLO EN ESCRITORIO SIN USUARIO
A24: 210000060347-0000 | B24: CGE002643 | C24: NOTEBOOK | D24: 1 | E24: SI | F24: NATHALY JAVIERA OLMOS CARVAJAL | G24: NJOLMOSC | H24: 5CD116Q46R | I24: NB5CD116Q46R | J24: HP | K24: PROBOOK 440 G7 | L24: PRESIDENTE RIESCO 5561 | M24: 15 | N24: LAS CONDES | O24: METROPOLITANA | P24: SANTIAGO | Q24: PLANIFICACION Y CONSTRUCCION DE LA RED | R24: NO | S24: CAMILA BRAVO | T24: INTERNO
A25: 210000060763-0000 | B25: CGE002727 | C25: NOTEBOOK | E25: NO | F25: Karin Valenzuela Fuenzalida | G25: kavalenzuelaf | H25: 5CS1463LF6 | I25: NB5CS1463LF6 | J25: HP | K25: PROBOOK 440 G9 | L25: Av Presidente riesco 5561 | M25: 12 | N25: Las Condes | O25: Metropolitana | P25: Santiago | Q25: Tesoreria | R25: SI | S25: Karin Valenzuela | T25: INTERNO
A26: 210000016488-0000 | B26: CGE002731 | C26: MONITOR | F26: Carolina Guardera Ortega | G26: Cguarderao | H26: CN0N300H64180 | J26: DELL | K26: E1709WC | L26: Av Presidente riesco 5561 | M26: 12 | N26: Las Condes | O26: Metropolitana | P26: Santiago | Q26: Tesoreria | R26: SI | S26: Karin Valenzuela | T26: INTERNO
A27: 210000044960-0000 | B27: CGE002734 | C27: NOTEBOOK | E27: SI | F27: Carolina Guardera Ortega | G27: Cguarderao | H27: 5CG63145YD | I27: NB5CG63145YD | J27: HP | K27: ELITEBOOK 840 G3 | L27: Av Presidente riesco 5561 | M27: 12 | N27: Las Condes | O27: Metropolitana | P27: Santiago | Q27: Tesoreria | R27: SI | S27: Karin Valenzuela | T27: INTERNO
A28: 210000062590-0000 | B28: CGE002736 | C28: NOTEBOOK | D28: 1 | E28: SI | F28: Evelyn Rodriguez Becerra | G28: ebrodriguezb | H28: 5CD236FGDD | I28: NB5CD236FGDD | J28: HP | K28: PROBOOK 440 G9 | L28: Av Presidente riesco 5561 | M28: 12 | N28: Las Condes | O28: Metropolitana | P28: Santiago | Q28: Tesoreria | R28: SI | S28: Karin Valenzuela | T28: INTERNO
A29: 210000045899-0000 | B29: CGE002739 | C29: NOTEBOOK | E29: NO | F29: Valeria Galaz Araya | G29: vcgalaza | H29: 5CG6402H0V | I29: NB5CG6402H0V | J29: HP | K29: ELITEBOOK 840 G3 | L29: Av Presidente riesco 5561 | M29: 12 | N29: Las Condes | O29: Metropolitana | P29: Santiago | Q29: Tesoreria | R29: SI | S29: Karin Valenzuela | T29: INTERNO
A30: 210000060798-0000 | B30: CGE003711 | C30: NOTEBOOK | D30: 1 | E30: SI | F30: DIEGO ANCAVIL CARRASCO | G30: DANCAVILC | H30: W009SEQ | I30: NBW-009SEQ | J30: LENOVO | K30: 20VL-S1FJ04 | L30: PRESIDENTE RIESCO 5561 | M30: 15 | N30: LAS CONDES | O30: METROPOLITANA | P30: SANTIAGO | Q30: PLANIFICACION Y CONSTRUCCION DE LA RED | R30: NO | S30: FELIPE GONZALEZ | T30: INTERNO
A31: NO TIENE | B31: CGE003712 | C31: MONITOR | D31: 1 | E31: SI | F31: DIEGO ANCAVIL CARRASCO | G31: DANCAVILC | H31: CN8X1R3 | I31: NO | J31: DELL | K31: P2422H | L31: PRESIDENTE RIESCO 5561 | M31: 15 | N31: LAS CONDES | O31: METROPOLITANA | P31: SANTIAGO | Q31: PLANIFICACION Y CONSTRUCCION DE LA RED | R31: NO | S31: FELIPE GONZALEZ | T31: INTERNO | V31: REVISAR POR CARINA GALLARDO
A32: 210000062798-0000 | B32: CGE004015 | C32: MONITOR | D32: 1 | E32: SI | F32: SEBASTIAN ECHEVERRIA | G32: SDECHEVERRIA | H32: 4X3ZH4TW205540J | I32: NO | J32: SAMSUNG | K32: S24A336NHL | L32: PRESIDENTE RIESCO 5561 | M32: 15 | N32: LAS CONDES | O32: METROPOLITANA | P32: SANTIAGO | Q32: ECONOMIA, DISEÑO Y TX | R32: NO | S32: NELSON ANTILLANCA | T32: INTERNO
A33: 210000062824-0000 | B33: CGE004041 | C33: MONITOR | F33: Enrique Aravena Cifuentes | G33: earavena | H33: 4X3ZH4TW206135Z | J33: Samsung | K33: S24A33 | L33: Av Presidente riesco 5561 | M33: 12 | N33: Las Condes | O33: Metropolitana | P33: Santiago | Q33: Tesoreria | R33: SI | S33: Karin Valenzuela | T33: INTERNO
A34: NO TIENE | B34: CGE004086 | C34: NOTEBOOK | D34: 1 | E34: SI | F34: SEBASTIAN ECHEVERRIA | G34: SDECHEVERRIA | H34: CD30855G0 | I34: NB5CD30855G0 | J34: HP | K34: PROBOOK 440 G9 | L34: PRESIDENTE RIESCO 5561 | M34: 15 | N34: LAS CONDES | O34: METROPOLITANA | P34: SANTIAGO | Q34: ECONOMIA, DISEÑO Y TX | R34: NO | S34: NELSON ANTILLANCA | T34: INTERNO | V34: REVISAR POR CARINA GALLARDO
A35: 210000062872-0000 | B35: CGE004099 | C35: MONITOR | F35: Yessica Perez Ibarra | G35: yperez | H35: 4X3ZH4TW203938H | J35: Samsung | K35: S24A33 | L35: Av Presidente riesco 5561 | M35: 12 | N35: Las Condes | O35: Metropolitana | P35: Santiago | Q35: Tesoreria | R35: SI | S35: Karin Valenzuela | T35: INTERNO
A36: NO TIENE | B36: CGE005199 | C36: NOTEBOOK | D36: 1 | E36: SI | F36: BEATRIZ GUERRA GACITUA | G36: BGUERRAG | H36: KZ79W3 | I36: NBKZ79W3 | J36: DELL | K36: LATITUDE 5440 | L36: PRESIDENTE RIESCO 5561 | M36: 15 | N36: LAS CONDES | O36: METROPOLITANA | P36: SANTIAGO | Q36: SUPERVICION DE SEGURIDAD | R36: NO | S36: CHRISTIAN OLAVE | T36: INTERNO | V36: REVISAR POR CARINA GALLARDO
A37: 210000063933-0000 | B37: CGE005319 | C37: MONITOR | D37: 1 | E37: NO | F37: GUILLERMO AYANCA GALLARDO | G37: GAYANCANG | H37: 7VHGTZ3 | I37: NO | J37: DELL | K37: P2422M | L37: PRESIDENTE RIESCO 5561 | M37: 15 | N37: LAS CONDES | O37: METROPOLITANA | P37: SANTIAGO | Q37: PLANIFICACION Y CONSTRUCCION DE LA RED | R37: NO | S37: CAMILA BRAVO | T37: INTERNO
A38: NO TIENE | B38: CGE005553 | C38: NOTEBOOK | D38: 1 | E38: SI | F38: YENNY LORETO DIAZ ORELLANA | G38: YLDIAZO | H38: 3BHB9W3 | I38: NB3BHB9W3 | J38: DELL | K38: LATITUDE 5440 13G | L38: PEDRO AGUIRRE CERDA 5558 | M38: 1 | N38: ANTOFAGASTA | O38: ANTOFAGASTA | P38: ANTOFAGASTA
A39: 210000065128-0000 | B39: CGE007923 | C39: NOTEBOOK | D39: 1 | E39: NO | H39: 5CD421CDJM | I39: NB5CD421CDJM | J39: HP | K39: PROBOOK 440 G9 | L39: PRESIDENTE RIESCO 5561 | M39: 14 | N39: LAS CONDES | O39: METROPOLITANA | P39: SANTIAGO | Q39: TRANSFORMACION DIGITAL | R39: NO | T39: INTERNO
A40: NO TIENE | B40: CGE007929 | C40: MONITOR | D40: 1 | E40: SI | F40: FABIOLA DUARTE MORALES | G40: FDUARTEM | H40: 307NDZJK4325 | I40: NO | J40: LG | K40: 23EA53VQ | L40: PRESIDENTE RIESCO 5561 | M40: 15 | N40: LAS CONDES | O40: METROPOLITANA | P40: SANTIAGO | Q40: ASUNTOS ADMINISTRATIVOS | R40: NO | S40: JAVIERA SANCHEZ | T40: INTERNO | V40: REVISAR POR CARINA GALLARDO
A41: 210000061049-0000 | B41: CGE008332 | C41: NOTEBOOK | D41: 1 | E41: SI | F41: VALERIA OLIVOS VALENZUELA | G41: VROLIVOSV | H41: 5CD207HCTW | I41: NB5CD207HCTW | J41: HP | K41: PROBOOK 440 G8 NOTEBOOK PC | L41: PDTE. RIESCO 5561 | M41: 12 | N41: LAS CONDES | O41: METROPOLITANA | P41: SANTIAGO | Q41: GESTIÓN FINANCIERA | R41: NO | S41: TOMÁS MORALES JAUREGUIBERRY | T41: INTERNO
A42: 210000060640-0000 | B42: CGE008388 | C42: MONITOR | D42: 1 | E42: SI | F42: MENGXUAN LIU | G42: NO | H42: 1CR1070D4T | I42: NO | J42: HP | K42: P24VG4 | L42: PRESIDENTE RIESCO 5561 | M42: 15 | N42: LAS CONDES | O42: METROPOLITANA | P42: SANTIAGO | Q42: PLANIFICACION Y CONSTRUCCION DE LA RED | R42: NO | S42: NO DISPONIBLE | T42: INTERNO | V42: USUARIA DE VACACIONES FALA INVENTARIAR EQUIPO
A43: 210000024769-0000 | B43: CGE008439 | C43: MONITOR | D43: 1 | E43: NO | F43: LEANDRO SALAS ALVARADO | G43: LSALASA | H43: CNC110NWF8 | I43: NO | J43: HP | K43: LE1711 | L43: PRESIDENTE RIESCO 5561 | M43: 15 | N43: LAS CONDES | O43: METROPOLITANA | P43: SANTIAGO | Q43: LICITACION Y PROPUESTA DE OBRAS TX | R43: NO | S43: NELSON ANTILLANCA | T43: INTERNO
A44: 210000065974-0000 | B44: CGE009095 | C44: PC | D44: 1 | E44: NO | F44: BASTIAN LEONEL ARREDONDO ACEITUNO | G44: BARREDONDOA | H44: NO DISPONIBLE | I44: NO DISPONIBLE | J44: HP | K44: ALL IN ONE | L44: PRESIDENTE RIESCO 5561 | M44: 15 | N44: LAS CONDES | O44: METROPOLITANA | P44: SANTIAGO | Q44: CONSTRUCCION TX | R44: NO | S44: NELSON ANTILLANCA | T44: INTERNO | V44: EQUIPO ALL IN ONE - USUARIO NO DISPONIBLE
A45: 210000066741-0000 | B45: CGE010218 | C45: NOTEBOOK | D45: 1 | E45: SI | F45: FERNANDO SANHUEZA | G45: FPSANHUEZAF | H45: PF5F5P1Q | I45: NBPF5F5P1Q | J45: LENOVO | K45: 21JL002HCL | L45: PRESIDENTE RIESCO 5561 | M45: 15 | N45: LAS CONDES | O45: METROPOLITANA | P45: SANTIAGO | Q45: PLANIFICACION Y CONSTRUCCION DE LA RED | R45: NO | S45: JORGE MUÑOZ | T45: INTERNO
A46: 210000066419-0000 | B46: CGE010633 | C46: PC | D46: 1 | E46: SI | F46: ESTEBAN ALARCON BERNAL | G46: EALARCONB | H46: NO DISPONIBLE | I46: NO DISPONIBLE | J46: LENOVO | K46: 12K9005LCS | L46: PRESIDENTE RIESCO 5561 | M46: 15 | N46: LAS CONDES | O46: METROPOLITANA | P46: SANTIAGO | Q46: LICITACION Y PROPUESTA DE OBRAS TX | R46: NO | S46: NELSON ANTILLANCA | T46: INTERNO | V46: EQUIPO ALL IN ONE - USUARIO NO DISPONIBLE
A47: 210000066558-0000 | B47: CGE010660 | C47: MONITOR | D47: 1 | E47: SI | F47: NATHALY JAVIERA OLMOS CARVAJAL | G47: NJOLMOSC | H47: W1D2451G1016 | I47: NO | J47: VIEWSONIC | K47: VG2456 | L47: PRESIDENTE RIESCO 5561 | M47: 15 | N47: LAS CONDES | O47: METROPOLITANA | P47: SANTIAGO | Q47: PLANIFICACION Y CONSTRUCCION DE LA RED | R47: NO | S47: CAMILA BRAVO | T47: INTERNO
A48: 210000066560-0000 | B48: CGE010662 | C48: MONITOR | D48: 1 | E48: SI | F48: BEATRIZ GUERRA GACITUA | G48: BGUERRAG | H48: W1D2451G0954 | I48: NO | J48: VIEWSONIC | K48: VG2456 | L48: PRESIDENTE RIESCO 5561 | M48: 15 | N48: LAS CONDES | O48: METROPOLITANA | P48: SANTIAGO | Q48: SUPERVICION DE SEGURIDAD | R48: NO | S48: CHRISTIAN OLAVE | T48: INTERNO
A49: 210000066651-0000 | B49: CGE010677 | C49: MONITOR | D49: 1 | E49: NO | F49: SOPORTE NI | G49: NO | H49: W1D2451G0952 | I49: NO | J49: VIEWSONIC | K49: VG2456 | L49: PRESIDENTE RIESCO 5561 | M49: 15 | N49: LAS CONDES | O49: METROPOLITANA | P49: SANTIAGO | Q49: PLANIFICACION Y CONSTRUCCION DE LA RED | R49: NO | S49: SOPORTE NI | T49: INTERNO | V49: MONITOR SOLO EN ESCRITORIO SIN USUARIO
A50: 210000066641-0000 | B50: CGE010678 | C50: MONITOR | D50: 1 | E50: SI | F50: FERNANDO SANHUEZA | G50: FPSANHUEZAF | H50: W1D2451G0946 | I50: NO | J50: VIEWSONIC | K50: VG2456 | L50: PRESIDENTE RIESCO 5561 | M50: 15 | N50: LAS CONDES | O50: METROPOLITANA | P50: SANTIAGO | Q50: PLANIFICACION Y CONSTRUCCION DE LA RED | R50: NO | S50: JORGE MUÑOZ | T50: INTERNO
A51: 210000066395-0000 | B51: CGE010777 | C51: PC | D51: 1 | E51: SI | F51: NATHALY JAVIERA OLMOS CARVAJAL | G51: NJOLMOSC | H51: MP2GDJ15 | I51: AIOMP2GDJ15 | J51: LENOVO | K51: 12K9005LCS | L51: PRESIDENTE RIESCO 5561 | M51: 15 | N51: LAS CONDES | O51: METROPOLITANA | P51: SANTIAGO | Q51: PLANIFICACION Y CONSTRUCCION DE LA RED | R51: NO | S51: CAMILA BRAVO | T51: INTERNO | V51: EQUIPO ALL IN ONE
A52: 210000066381-0000 | B52: CGE010791 | C52: PC | D52: 1 | E52: NO | F52: ANGELY CAMPOS TRINCADO | G52: ATCAMPOST | H52: MP2GC8YR | I52: AIOMP2GC8YR | J52: LENOVO | K52: 12K9005LCS | L52: PDTE. RIESCO 5561 | M52: 12 | N52: LAS CONDES | O52: METROPOLITANA | P52: SANTIAGO | Q52: COMPRAS Y LOGÍSTICA | R52: NO | S52: RODRIGO PARRAGUEZ CORDOVA | T52: INTERNO | V52: USUARIA CONSULTA POR POSIBILIDAD DE ACTUALIZACIÓN DE EQUIPO (EL AIO QUE USA ES MUY ANTIGUO)
A53: 210000066345-0000 | B53: CGE010827 | C53: PC | D53: 1 | E53: NO | F53: JOAQUIN LEON LEON | G53: JALEONR | H53: MP2GDFRM | I53: AIOMP2GDFRM | J53: LENOVO | K53: 12K9005LCS | L53: PRESIDENTE RIESCO 5561 | M53: 15 | N53: LAS CONDES | O53: METROPOLITANA | P53: SANTIAGO | Q53: LICITACION Y PROPUESTA DE OBRAS TX | R53: NO | S53: NELSON ANTILLANCA | T53: INTERNO | V53: EQUIPO ALL IN ONE
A54: 210000066329-0000 | B54: CGE010843 | C54: PC | D54: 1 | E54: NO | F54: LEANDRO SALAS ALVARADO | G54: LSALASA | H54: NO DISPONIBLE | I54: NO DISPONIBLE | J54: LENOVO | K54: 12K9005LCS | L54: PRESIDENTE RIESCO 5561 | M54: 15 | N54: LAS CONDES | O54: METROPOLITANA | P54: SANTIAGO | Q54: LICITACION Y PROPUESTA DE OBRAS TX | R54: NO | S54: NELSON ANTILLANCA | T54: INTERNO | V54: EQUIPO ALL IN ONE - USUARIO NO DISPONIBLE
A55: 210000066328-0000 | B55: CGE010844 | C55: PC | D55: 1 | E55: NO | F55: LAURA D'ORAZIO CORDOVA | G55: LDORAZIOC | H55: NO DISPONIBLE | I55: NO DISPONIBLE | J55: LENOVO | K55: 12K9005LCS | L55: PRESIDENTE RIESCO 5561 | M55: 15 | N55: LAS CONDES | O55: METROPOLITANA | P55: SANTIAGO | Q55: LICITACION Y PROPUESTA DE OBRAS TX | R55: NO | S55: NELSON ANTILLANCA | T55: INTERNO | V55: EQUIPO ALL IN ONE - USUARIO NO DISPONIBLE
A56: 210000066754-0000 | B56: CGE010909 | C56: NOTEBOOK | D56: 1 | E56: SI | F56: PEDRO CORDOVA GALVEZ | G56: PCORDOVAG | H56: PF5F5517 | I56: NBPF5F5517 | J56: LENOVO | K56: 21JL002HCL | L56: PRESIDENTE RIESCO 5561 | M56: 15 | N56: LAS CONDES | O56: METROPOLITANA | P56: SANTIAGO | Q56: PLANIFICACION Y CONSTRUCCION DE LA RED | R56: NO | S56: FERNANDO SANHUEZA | T56: INTERNO
A57: NO TIENE | B57: CGE011017 | C57: PC | D57: 1 | E57: SI | F57: PEDRO VARGAS ABURTO | G57: PJVARGASA | H57: 43319034105 | I57: PC43319034105 | J57: WLAMENWEG | K57: R10 | L57: PRESIDENTE RIESCO 5561 | M57: 15 | N57: LAS CONDES | O57: METROPOLITANA | P57: SANTIAGO | Q57: PLANIFICACION Y CONSTRUCCION DE LA RED | R57: NO | S57: ADAM CASTILLO SALAS | T57: INTERNO | U57: SE COLOCA ETIQUETA ENTEL | V57: REVISAR POR CARINA GALLARDO
A58: NO TIENE | B58: CGE011018 | C58: MONITOR | D58: 1 | E58: SI | F58: PEDRO VARGAS ABURTO | G58: PJVARGASA | H58: DR77655H724 | I58: NO | J58: LG | K58: W1921 | L58: PRESIDENTE RIESCO 5561 | M58: 15 | N58: LAS CONDES | O58: METROPOLITANA | P58: SANTIAGO | Q58: PLANIFICACION Y CONSTRUCCION DE LA RED | R58: NO | S58: ADAM CASTILLO SALAS | T58: INTERNO | U58: SE COLOCA ETIQUETA ENTEL | V58: REVISAR POR CARINA GALLARDO
A59: 210000065927-0000 | B59: CGE011019 | C59: NOTEBOOK | D59: 1 | E59: SI | F59: FABIOLA DUARTE MORALES | G59: FDUARTEM | H59: 5CD451FWMN | I59: NB5CD451FWMN | J59: HP | K59: PROBOOK 440 G10 | L59: PRESIDENTE RIESCO 5561 | M59: 15 | N59: LAS CONDES | O59: METROPOLITANA | P59: SANTIAGO | Q59: ASUNTOS ADMINISTRATIVOS | R59: NO | S59: JAVIERA SANCHEZ | T59: INTERNO | U59: SE COLOCA ETIQUETA ENTEL
A60: 210000021081-0000 | B60: CGE011020 | C60: MONITOR | D60: 1 | E60: NO | F60: BASTIAN LEONEL ARREDONDO ACEITUNO | G60: BARREDONDOA | H60: CN0X706H7287205D160L | I60: NO | J60: DELL | K60: E1709W | L60: PRESIDENTE RIESCO 5561 | M60: 15 | N60: LAS CONDES | O60: METROPOLITANA | P60: SANTIAGO | Q60: CONSTRUCCION TX | R60: NO | S60: NELSON ANTILLANCA | T60: INTERNO | U60: SE COLOCA ETIQUETA ENTEL
A61: 210000028621-0000 | B61: CGE011021 | C61: MONITOR | D61: 1 | E61: NO | F61: JOAQUIN LEON LEON | G61: JALEONR | H61: CNC145P3R3 | I61: NO | J61: HP | K61: EM886A | L61: PRESIDENTE RIESCO 5561 | M61: 15 | N61: LAS CONDES | O61: METROPOLITANA | P61: SANTIAGO | Q61: LICITACION Y PROPUESTA DE OBRAS TX | R61: NO | S61: NELSON ANTILLANCA | T61: INTERNO | U61: SE COLOCA ETIQUETA ENTEL
